Workbook

Sheet Scenario Comparison
A1: GuardSpine Financial Model -- Scenario Comparison
A2: Prepared for Kristen Hengst Smith meeting | Feb 19, 2026
A3: $1M raise at $9M pre-money / $10M post-money | 10% dilution
A5: Metric | B5: Bear Case | C5: Base Case | D5: Bull Case
A6: ASSUMPTIONS
A7: Starting Price (monthly) | B7: 2000 | C7: 2500 | D7: 3500
A8: Y1 Monthly Growth Rate | B8: 0.1 | C8: 0.15 | D8: 0.2
A9: Monthly Churn Rate | B9: 0.005 | C9: 0.003 | D9: 0.002
A10: Starting Customers | B10: 1 | C10: 1 | D10: 2
A11: Team Size (end Y1) | B11: 4 | C11: 5 | D11: 6
A12: REVENUE
A13: Y1 Total Revenue | B13: 254797.18 | C13: 392518.56 | D13: 1269645.5
A14: Y2 Total Revenue | B14: 920846.7 | C14: 1796344.2 | D14: 7003650.8
A15: End-of-Y1 MRR | B15: 41911.673 | C15: 69997.779 | D15: 240496.57
A16: End-of-Y2 MRR | B16: 110584.17 | C16: 234818.8 | D16: 977965.82
A17: End-of-Y1 ARR | B17: 502940.07 | C17: 839973.35 | D17: 2885958.8
A18: End-of-Y2 ARR | B18: 1327010 | C18: 2817825.6 | D18: 11735590
A19: End-of-Y1 Customers | B19: 21 | C19: 28 | D19: 69
A20: End-of-Y2 Customers | B20: 50 | C20: 81 | D20: 233
A21: MARGINS
A22: End-of-Y1 Gross Margin | B22: 0.93421045 | C22: 0.94857075 | D22: 0.9637629
A23: End-of-Y2 Gross Margin | B23: 0.95643567 | C23: 0.9636121 | D23: 0.9684662
A24: Y1 EBITDA | B24: -274538.57 | C24: -199212.11 | D24: 534973.38
A25: Y2 EBITDA | B25: 281566.5 | C25: 958269.21 | D25: 5624918.2
A26: End-of-Y2 EBITDA Margin | B26: 0.49070851 | C26: 0.66995533 | D26: 0.84622783
A27: SaaS OPERATING METRICS (End of Y2)
A28: LTV:CAC Ratio | B28: 77.15991 | C28: 198.76178 | D28: 397.23383
A29: CAC Payback (months) | B29: 2.1600163 | C29: 1.2577871 | D29: 0.83913632
A30: Net Revenue Retention | B30: 1.0652884 | C30: 1.0839689 | D30: 1.1003024
A31: Rule of 40 | B31: 1.2741689 | C31: 1.6775816 | D31: 2.0498565
A32: EFFICIENCY: ARR per Employee
A33: Team Size (end Y2) | B33: 4 | C33: 5 | D33: 6
A34: End-Y2 ARR / Employee | B34: 331752.5 | C34: 563565.12 | D34: 1955931.6
A35: CASH & RUNWAY
A36: EBITDA Breakeven (month #) | B36: 14 | C36: 12 | D36: 5
A37: End-of-Y1 Cash Remaining | B37: 725461.43 | C37: 800787.89 | D37: 1534973.4
A38: End-of-Y2 Cash Remaining | B38: 1007027.9 | C38: 1759057.1 | D38: 7159891.6
A39: Peak Monthly Burn | B39: 32554.1 | C39: 31482.575 | D39: 22493.14
A42: KEY DIFFERENTIATOR: BYOK Architecture
A43: Customers bring their own LLM API keys. GuardSpine pays ZERO inference costs.
A44: Result: 90%+ gross margins at scale vs 40-65% for typical AI companies.
A45: Comparable: Datadog (80.8% GM), CrowdStrike (75% GM), Zscaler (73.7% GM)
A46: GuardSpine exceeds all comparables because BYOK eliminates the #1 AI cost driver.
A48: BULL CASE DRIVERS: AI Adoption Tailwinds
A49: - AI coding tools market: $7.37B in 2025, projected $12-15B by 2027 (35-40% CAGR)
A50: - GitHub Copilot: 20M users, 4.7M paid subscribers, 50K+ orgs, 90% of Fortune 100
A51: - 75% of enterprise devs will use AI code assistants by 2028 (Gartner), up from <10% in 2023
A52: - AI governance platform market: $492M in 2026, >$1B by 2030 (Gartner, 28%+ CAGR)
A53: - EU AI Act high-risk rules enforcement: August 2026 -- compliance spending $2-15M per firm
A54: - DORA enforceable since Jan 2025; aligns with AI Act governance controls
... A59: AI-NATIVE BENCHMARKS: ARR per Employee
A60: Company | B60: ARR | C60: Team Size | D60: ARR/Employee
A61: Midjourney (2025) | B61: 200000000 | C61: 11 | D61: 18181818
A62: Cursor / Anysphere (Nov 2025) | B62: 1000000000 | C62: 150 | D62: 6666667
A63: Cursor / Anysphere (early 2025) | B63: 100000000 | C63: 20 | D63: 5000000
A64: Mercor (2025) | B64: -- | C64: -- | D64: 4500000
A65: Nvidia (FY 2025) | B65: -- | C65: -- | D65: 3600000
A66: Meta (FY 2024) | B66: -- | C66: -- | D66: 2200000
A67: Microsoft (FY 2024) | B67: -- | C67: -- | D67: 1800000
A68: GuardSpine BEAR (end Y2) | B68: 1327010 | C68: 4 | D68: 331752.5
A69: GuardSpine BASE (end Y2) | B69: 2817825.6 | C69: 5 | D69: 563565.12
A70: GuardSpine BULL (end Y2) | B70: 11735590 | C70: 6 | D70: 1955931.6
A72: AI-native startups avg $3.5M ARR/employee vs traditional SaaS $200-400K.
A73: GuardSpine's BYOK + PLG model = Cursor-class efficiency without inference cost drag.
A74: Sources: Sacra, SaaStr, CB Insights, Lean AI Leaderboard, company filings (2025-2026)

Sheet Recap
C1: Year 1 | E1: Year 2
A2: Revenue
B3: ARR | D3: =sum('Financial Model'!C66:N66) | F3: =sum('Financial Model'!O66:Z66) | H3: Note: To edit the numbers, first make a copy of this sheet (File > Make a copy).
A5: Costs | H5: Made by Gary Gaspar
B6: Costs of Good Sold | C6: =D6/$D$3 | D6: =sum('Financial Model'!C71:N71) | E6: =F6/$F$3 | F6: =sum('Financial Model'!O71:Z71) | H6: =HYPERLINK("https://marker.io?utm_source=spreadsheet&utm_medium=template&utm_campaign=saas-financial-model","https://marker.io")
B7: Sales & Marketing | C7: =D7/$D$3 | D7: =sum('Financial Model'!C77:N77) | E7: =F7/$F$3 | F7: =sum('Financial Model'!O77:Z77)
B8: Research & Development | C8: =D8/$D$3 | D8: =sum('Financial Model'!C80:N80) | E8: =F8/$F$3 | F8: =sum('Financial Model'!O80:Z80)
B9: General & Administrative | C9: =D9/$D$3 | D9: =sum('Financial Model'!C83:N83) | E9: =F9/$F$3 | F9: =sum('Financial Model'!O83:Z83)
A11: EBIT | D11: =D3-sum(D6:D9) | F11: =F3-sum(F6:F9)
A14: Cash needed to cover costs | F14: =sumif('Financial Model'!C87:Z87,"<0")

Sheet Growth Hypotheses
B1: Year 1 | F1: Year 2
A2: Hypotheses | B2: Q1 | C2: Q2 | D2: Q3 | E2: Q4 | F2: Q1 | G2: Q2 | H2: Q3 | I2: Q4
A3: Average monthly price of subscriptions | B3: 2500 | C3: 2500 | D3: 2500 | E3: 2500 | F3: 2900 | G3: 2900 | H3: 2900 | I3: 2900
A4: Monthly growth rate in number of new customer | B4: 0.15 | C4: 0.12 | D4: 0.1 | E4: 0.08 | F4: 0.08 | G4: 0.07 | H4: 0.06 | I4: 0.05
A5: Monthly revenue churn rate | B5: 0.003 | C5: 0.003 | D5: 0.004 | E5: 0.004 | F5: 0.004 | G5: 0.004 | H5: 0.004 | I5: 0.004
A8: Number of new customers added last month | B8: 1 | C8: Cannot be ZERO
A9: Starting MRR | B9: 2500

Sheet Costs Hypotheses
A1: Personnel
C2: Name (optional) | D2: Yearly Cost (tax included) | E2: Starting month | F2: Category
B3: CEO | C3: David Youssef | D3: 120000 | E3: 1 | F3: =if(or(B3="CEO",B3="CTO"),"General & Administrative",if(B3="Engineer","Research & Development",if(or(B3="Customer Success",B3="Sales",B3="Marketing"),"Sales & Marketing",if(B3="Support","Support","N/A"))))
B4: Engineer | C4: Igor Malovitsa (CTO) | D4: 120000 | E4: 1 | F4: =if(or(B4="CEO",B4="CTO"),"General & Administrative",if(B4="Engineer","Research & Development",if(or(B4="Customer Success",B4="Sales",B4="Marketing"),"Sales & Marketing",if(B4="Support","Support","N/A"))))
B5: Engineer | C5: Eng Hire #1 | D5: 120000 | E5: 4 | F5: =if(or(B5="CEO",B5="CTO"),"General & Administrative",if(B5="Engineer","Research & Development",if(or(B5="Customer Success",B5="Sales",B5="Marketing"),"Sales & Marketing",if(B5="Support","Support","N/A"))))
B6: Engineer | C6: Eng Hire #2 | D6: 120000 | E6: 10 | F6: =if(or(B6="CEO",B6="CTO"),"General & Administrative",if(B6="Engineer","Research & Development",if(or(B6="Customer Success",B6="Sales",B6="Marketing"),"Sales & Marketing",if(B6="Support","Support","N/A"))))
F7: =if(or(B7="CEO",B7="CTO"),"General & Administrative",if(B7="Engineer","Research & Development",if(or(B7="Customer Success",B7="Sales",B7="Marketing"),"Sales & Marketing",if(B7="Support","Support","N/A"))))
F8: =if(or(B8="CEO",B8="CTO"),"General & Administrative",if(B8="Engineer","Research & Development",if(or(B8="Customer Success",B8="Sales",B8="Marketing"),"Sales & Marketing",if(B8="Support","Support","N/A"))))
F9: =if(or(B9="CEO",B9="CTO"),"General & Administrative",if(B9="Engineer","Research & Development",if(or(B9="Customer Success",B9="Sales",B9="Marketing"),"Sales & Marketing",if(B9="Support","Support","N/A"))))
F10: =if(or(B10="CEO",B10="CTO"),"General & Administrative",if(B10="Engineer","Research & Development",if(or(B10="Customer Success",B10="Sales",B10="Marketing"),"Sales & Marketing",if(B10="Support","Support","N/A"))))
F11: =if(or(B11="CEO",B11="CTO"),"General & Administrative",if(B11="Engineer","Research & Development",if(or(B11="Customer Success",B11="Sales",B11="Marketing"),"Sales & Marketing",if(B11="Support","Support","N/A"))))
F12: =if(or(B12="CEO",B12="CTO"),"General & Administrative",if(B12="Engineer","Research & Development",if(or(B12="Customer Success",B12="Sales",B12="Marketing"),"Sales & Marketing",if(B12="Support","Support","N/A"))))
F13: =if(or(B13="CEO",B13="CTO"),"General & Administrative",if(B13="Engineer","Research & Development",if(or(B13="Customer Success",B13="Sales",B13="Marketing"),"Sales & Marketing",if(B13="Support","Support","N/A"))))
F14: =if(or(B14="CEO",B14="CTO"),"General & Administrative",if(B14="Engineer","Research & Development",if(or(B14="Customer Success",B14="Sales",B14="Marketing"),"Sales & Marketing",if(B14="Support","Support","N/A"))))
F15: =if(or(B15="CEO",B15="CTO"),"General & Administrative",if(B15="Engineer","Research & Development",if(or(B15="Customer Success",B15="Sales",B15="Marketing"),"Sales & Marketing",if(B15="Support","Support","N/A"))))
F16: =if(or(B16="CEO",B16="CTO"),"General & Administrative",if(B16="Engineer","Research & Development",if(or(B16="Customer Success",B16="Sales",B16="Marketing"),"Sales & Marketing",if(B16="Support","Support","N/A"))))
F17: =if(or(B17="CEO",B17="CTO"),"General & Administrative",if(B17="Engineer","Research & Development",if(or(B17="Customer Success",B17="Sales",B17="Marketing"),"Sales & Marketing",if(B17="Support","Support","N/A"))))
F18: =if(or(B18="CEO",B18="CTO"),"General & Administrative",if(B18="Engineer","Research & Development",if(or(B18="Customer Success",B18="Sales",B18="Marketing"),"Sales & Marketing",if(B18="Support","Support","N/A"))))
... F22: =if(or(B22="CEO",B22="CTO"),"General & Administrative",if(B22="Engineer","Research & Development",if(or(B22="Customer Success",B22="Sales",B22="Marketing"),"Sales & Marketing",if(B22="Support","Support","N/A"))))
A24: Marketing spending
D25: % of MRR
B26: Adwords | D26: 0.02
B27: Social / display ads | D27: 0.01
A29: Cost of good sold
B30: Payement Processing fees | D30: 0.03
B31: Hosting & Bandwidth | D31: 1500
A33: Miscellaneous
B34: AI Agent APIs (3 x $1K/mo) | D34: 3000
B35: Software subscriptions (CRM, monitoring) | D35: 1000
B36: Legal, accountants, IP/patents | D36: 2000
B37: Travel / conferences | D37: 500
B38: Remote work (no office) | D38: 0
B39: Internet, supplies | D39: 200
B40: Insurance (D&O, E&O) | D40: 667
B41: Content / SEO / community | D41: 500
B42: Cognitive attestation license (future) | D42: 0

Sheet Financial Model
C1: Year 1 | O1: Year 2
A2: Month | C2: 42736 | D2: 42767 | E2: 42795 | F2: 42826 | G2: 42856 | H2: 42887 | I2: 42917 | J2: 42948 | K2: 42979 | L2: 43009 | M2: 43040 | N2: 43070 | O2: 43101 | P2: 43132 | Q2: 43160 | R2: 43191 | S2: 43221 | T2: 43252 | U2: 43282 | V2: 43313 | W2: 43344 | X2: 43374 | Y2: 43405 | Z2: 43435
A3: Month N | C3: 1 | D3: 2 | E3: 3 | F3: 4 | G3: 5 | H3: 6 | I3: 7 | J3: 8 | K3: 9 | L3: 10 | M3: 11 | N3: 12 | O3: 13 | P3: 14 | Q3: 15 | R3: 16 | S3: 17 | T3: 18 | U3: 19 | V3: 20 | W3: 21 | X3: 22 | Y3: 23 | Z3: 24
A4: REVENUE
A6: Revenue & customer Growth
B7: Average revenue per new customer | C7: ='Growth Hypotheses'!B3 | D7: ='Growth Hypotheses'!B3 | E7: ='Growth Hypotheses'!B3 | F7: ='Growth Hypotheses'!C3 | G7: ='Growth Hypotheses'!C3 | H7: ='Growth Hypotheses'!C3 | I7: ='Growth Hypotheses'!D3 | J7: ='Growth Hypotheses'!D3 | K7: ='Growth Hypotheses'!D3 | L7: ='Growth Hypotheses'!E3 | M7: ='Growth Hypotheses'!E3 | N7: ='Growth Hypotheses'!E3 | O7: ='Growth Hypotheses'!F3 | P7: ='Growth Hypotheses'!F3 | Q7: ='Growth Hypotheses'!F3 | R7: ='Growth Hypotheses'!G3 | S7: ='Growth Hypotheses'!G3 | T7: ='Growth Hypotheses'!G3 | U7: ='Growth Hypotheses'!H3 | V7: ='Growth Hypotheses'!H3 | W7: ='Growth Hypotheses'!H3 | X7: ='Growth Hypotheses'!I3 | Y7: ='Growth Hypotheses'!I3 | Z7: ='Growth Hypotheses'!I3
B8: New customers | C8: ='Growth Hypotheses'!B8+('Growth Hypotheses'!B8*'Growth Hypotheses'!B4) | D8: =C8+(C8*'Growth Hypotheses'!B4) | E8: =D8+(D8*'Growth Hypotheses'!B4) | F8: =E8+(E8*'Growth Hypotheses'!C4) | G8: =F8+(F8*'Growth Hypotheses'!C4) | H8: =G8+(G8*'Growth Hypotheses'!C4) | I8: =H8+(H8*'Growth Hypotheses'!D4) | J8: =I8+(I8*'Growth Hypotheses'!D4) | K8: =J8+(J8*'Growth Hypotheses'!D4) | L8: =K8+(K8*'Growth Hypotheses'!E4) | M8: =L8+(L8*'Growth Hypotheses'!E4) | N8: =M8+(M8*'Growth Hypotheses'!E4) | O8: =N8+(N8*'Growth Hypotheses'!F4) | P8: =O8+(O8*'Growth Hypotheses'!F4) | Q8: =P8+(P8*'Growth Hypotheses'!F4) | R8: =Q8+(Q8*'Growth Hypotheses'!G4) | S8: =R8+(R8*'Growth Hypotheses'!G4) | T8: =S8+(S8*'Growth Hypotheses'!G4) | U8: =T8+(T8*'Growth Hypotheses'!H4) | V8: =U8+(U8*'Growth Hypotheses'!H4) | W8: =V8+(V8*'Growth Hypotheses'!H4) | X8: =W8+(W8*'Growth Hypotheses'!I4) | Y8: =X8+(X8*'Growth Hypotheses'!I4) | Z8: =Y8+(Y8*'Growth Hypotheses'!I4)
B9: Churn Rate | C9: ='Growth Hypotheses'!B5 | D9: ='Growth Hypotheses'!B5 | E9: ='Growth Hypotheses'!B5 | F9: ='Growth Hypotheses'!C5 | G9: ='Growth Hypotheses'!C5 | H9: ='Growth Hypotheses'!C5 | I9: ='Growth Hypotheses'!D5 | J9: ='Growth Hypotheses'!D5 | K9: ='Growth Hypotheses'!D5 | L9: ='Growth Hypotheses'!E5 | M9: ='Growth Hypotheses'!E5 | N9: ='Growth Hypotheses'!E5 | O9: ='Growth Hypotheses'!F5 | P9: ='Growth Hypotheses'!F5 | Q9: ='Growth Hypotheses'!F5 | R9: ='Growth Hypotheses'!G5 | S9: ='Growth Hypotheses'!G5 | T9: ='Growth Hypotheses'!G5 | U9: ='Growth Hypotheses'!H5 | V9: ='Growth Hypotheses'!H5 | W9: ='Growth Hypotheses'!H5 | X9: ='Growth Hypotheses'!I5 | Y9: ='Growth Hypotheses'!I5 | Z9: ='Growth Hypotheses'!I5
A10: Month Recurring Revenue
B11: New MRR | C11: =C8*C7 | D11: =D8*D7 | E11: =E8*E7 | F11: =F8*F7 | G11: =G8*G7 | H11: =H8*H7 | I11: =I8*I7 | J11: =J8*J7 | ... Z11: =Z8*Z7
B12: Lost MRR | C12: =C13*C9 | D12: =D13*D9 | E12: =E13*E9 | F12: =F13*F9 | G12: =G13*G9 | H12: =H13*H9 | I12: =I13*I9 | J12: =J13*J9 | ... Z12: =Z13*Z9
B13: MRR from last month | C13: ='Growth Hypotheses'!B9 | D13: =C14 | E13: =D14 | F13: =E14 | G13: =F14 | H13: =G14 | I13: =H14 | J13: =I14 | K13: =J14 | ... Z13: =Y14
B14: Gross MRR | C14: =C13+C11-C12 | D14: =D13+D11-D12 | E14: =E13+E11-E12 | F14: =F13+F11-F12 | G14: =G13+G11-G12 | H14: =H13+H11-H12 | I14: =I13+I11-I12 | J14: =J13+J11-J12 | ... Z14: =Z13+Z11-Z12
B15: MRR Growth rate | D15: =(D14-C14)/C14 | E15: =(E14-D14)/D14 | F15: =(F14-E14)/E14 | G15: =(G14-F14)/F14 | H15: =(H14-G14)/G14 | I15: =(I14-H14)/H14 | J15: =(J14-I14)/I14 | K15: =(K14-J14)/J14 | ... Z15: =(Z14-Y14)/Y14
B16: Payment Processing | C16: =C14*'Costs Hypotheses'!$D$30 | D16: =D14*'Costs Hypotheses'!$D$30 | E16: =E14*'Costs Hypotheses'!$D$30 | F16: =F14*'Costs Hypotheses'!$D$30 | G16: =G14*'Costs Hypotheses'!$D$30 | H16: =H14*'Costs Hypotheses'!$D$30 | I16: =I14*'Costs Hypotheses'!$D$30 | J16: =J14*'Costs Hypotheses'!$D$30 | ... Z16: =Z14*'Costs Hypotheses'!$D$30
B17: Net MRR | C17: =C14-C16 | D17: =D14-D16 | E17: =E14-E16 | F17: =F14-F16 | G17: =G14-G16 | H17: =H14-H16 | I17: =I14-I16 | J17: =J14-J16 | ... Z17: =Z14-Z16
A19: COSTS
A21: Personnel
B22: =+CONCATENATE('Costs Hypotheses'!B3," - ",'Costs Hypotheses'!C3) | C22: =if('Costs Hypotheses'!$E3<=C$3,('Costs Hypotheses'!$D3/12),0) | D22: =if('Costs Hypotheses'!$E3<=D$3,('Costs Hypotheses'!$D3/12),0) | E22: =if('Costs Hypotheses'!$E3<=E$3,('Costs Hypotheses'!$D3/12),0) | F22: =if('Costs Hypotheses'!$E3<=F$3,('Costs Hypotheses'!$D3/12),0) | G22: =if('Costs Hypotheses'!$E3<=G$3,('Costs Hypotheses'!$D3/12),0) | H22: =if('Costs Hypotheses'!$E3<=H$3,('Costs Hypotheses'!$D3/12),0) | I22: =if('Costs Hypotheses'!$E3<=I$3,('Costs Hypotheses'!$D3/12),0) | J22: =if('Costs Hypotheses'!$E3<=J$3,('Costs Hypotheses'!$D3/12),0) | ... Z22: =if('Costs Hypotheses'!$E3<=Z$3,('Costs Hypotheses'!$D3/12),0)
B23: =+CONCATENATE('Costs Hypotheses'!B4," - ",'Costs Hypotheses'!C4) | C23: =if('Costs Hypotheses'!$E4<=C$3,('Costs Hypotheses'!$D4/12),0) | D23: =if('Costs Hypotheses'!$E4<=D$3,('Costs Hypotheses'!$D4/12),0) | E23: =if('Costs Hypotheses'!$E4<=E$3,('Costs Hypotheses'!$D4/12),0) | F23: =if('Costs Hypotheses'!$E4<=F$3,('Costs Hypotheses'!$D4/12),0) | G23: =if('Costs Hypotheses'!$E4<=G$3,('Costs Hypotheses'!$D4/12),0) | H23: =if('Costs Hypotheses'!$E4<=H$3,('Costs Hypotheses'!$D4/12),0) | I23: =if('Costs Hypotheses'!$E4<=I$3,('Costs Hypotheses'!$D4/12),0) | J23: =if('Costs Hypotheses'!$E4<=J$3,('Costs Hypotheses'!$D4/12),0) | ... Z23: =if('Costs Hypotheses'!$E4<=Z$3,('Costs Hypotheses'!$D4/12),0)
B24: =+CONCATENATE('Costs Hypotheses'!B5," - ",'Costs Hypotheses'!C5) | C24: =if('Costs Hypotheses'!$E5<=C$3,('Costs Hypotheses'!$D5/12),0) | D24: =if('Costs Hypotheses'!$E5<=D$3,('Costs Hypotheses'!$D5/12),0) | E24: =if('Costs Hypotheses'!$E5<=E$3,('Costs Hypotheses'!$D5/12),0) | F24: =if('Costs Hypotheses'!$E5<=F$3,('Costs Hypotheses'!$D5/12),0) | G24: =if('Costs Hypotheses'!$E5<=G$3,('Costs Hypotheses'!$D5/12),0) | H24: =if('Costs Hypotheses'!$E5<=H$3,('Costs Hypotheses'!$D5/12),0) | I24: =if('Costs Hypotheses'!$E5<=I$3,('Costs Hypotheses'!$D5/12),0) | J24: =if('Costs Hypotheses'!$E5<=J$3,('Costs Hypotheses'!$D5/12),0) | ... Z24: =if('Costs Hypotheses'!$E5<=Z$3,('Costs Hypotheses'!$D5/12),0)
B25: =+CONCATENATE('Costs Hypotheses'!B6," - ",'Costs Hypotheses'!C6) | C25: =if('Costs Hypotheses'!$E6<=C$3,('Costs Hypotheses'!$D6/12),0) | D25: =if('Costs Hypotheses'!$E6<=D$3,('Costs Hypotheses'!$D6/12),0) | E25: =if('Costs Hypotheses'!$E6<=E$3,('Costs Hypotheses'!$D6/12),0) | F25: =if('Costs Hypotheses'!$E6<=F$3,('Costs Hypotheses'!$D6/12),0) | G25: =if('Costs Hypotheses'!$E6<=G$3,('Costs Hypotheses'!$D6/12),0) | H25: =if('Costs Hypotheses'!$E6<=H$3,('Costs Hypotheses'!$D6/12),0) | I25: =if('Costs Hypotheses'!$E6<=I$3,('Costs Hypotheses'!$D6/12),0) | J25: =if('Costs Hypotheses'!$E6<=J$3,('Costs Hypotheses'!$D6/12),0) | ... Z25: =if('Costs Hypotheses'!$E6<=Z$3,('Costs Hypotheses'!$D6/12),0)
B26: =+CONCATENATE('Costs Hypotheses'!B7," - ",'Costs Hypotheses'!C7) | C26: =if('Costs Hypotheses'!$E7<=C$3,('Costs Hypotheses'!$D7/12),0) | D26: =if('Costs Hypotheses'!$E7<=D$3,('Costs Hypotheses'!$D7/12),0) | E26: =if('Costs Hypotheses'!$E7<=E$3,('Costs Hypotheses'!$D7/12),0) | F26: =if('Costs Hypotheses'!$E7<=F$3,('Costs Hypotheses'!$D7/12),0) | G26: =if('Costs Hypotheses'!$E7<=G$3,('Costs Hypotheses'!$D7/12),0) | H26: =if('Costs Hypotheses'!$E7<=H$3,('Costs Hypotheses'!$D7/12),0) | I26: =if('Costs Hypotheses'!$E7<=I$3,('Costs Hypotheses'!$D7/12),0) | J26: =if('Costs Hypotheses'!$E7<=J$3,('Costs Hypotheses'!$D7/12),0) | ... Z26: =if('Costs Hypotheses'!$E7<=Z$3,('Costs Hypotheses'!$D7/12),0)
B27: =+CONCATENATE('Costs Hypotheses'!B8," - ",'Costs Hypotheses'!C8) | C27: =if('Costs Hypotheses'!$E8<=C$3,('Costs Hypotheses'!$D8/12),0) | D27: =if('Costs Hypotheses'!$E8<=D$3,('Costs Hypotheses'!$D8/12),0) | E27: =if('Costs Hypotheses'!$E8<=E$3,('Costs Hypotheses'!$D8/12),0) | F27: =if('Costs Hypotheses'!$E8<=F$3,('Costs Hypotheses'!$D8/12),0) | G27: =if('Costs Hypotheses'!$E8<=G$3,('Costs Hypotheses'!$D8/12),0) | H27: =if('Costs Hypotheses'!$E8<=H$3,('Costs Hypotheses'!$D8/12),0) | I27: =if('Costs Hypotheses'!$E8<=I$3,('Costs Hypotheses'!$D8/12),0) | J27: =if('Costs Hypotheses'!$E8<=J$3,('Costs Hypotheses'!$D8/12),0) | ... Z27: =if('Costs Hypotheses'!$E8<=Z$3,('Costs Hypotheses'!$D8/12),0)
B28: =+CONCATENATE('Costs Hypotheses'!B9," - ",'Costs Hypotheses'!C9) | C28: =if('Costs Hypotheses'!$E9<=C$3,('Costs Hypotheses'!$D9/12),0) | D28: =if('Costs Hypotheses'!$E9<=D$3,('Costs Hypotheses'!$D9/12),0) | E28: =if('Costs Hypotheses'!$E9<=E$3,('Costs Hypotheses'!$D9/12),0) | F28: =if('Costs Hypotheses'!$E9<=F$3,('Costs Hypotheses'!$D9/12),0) | G28: =if('Costs Hypotheses'!$E9<=G$3,('Costs Hypotheses'!$D9/12),0) | H28: =if('Costs Hypotheses'!$E9<=H$3,('Costs Hypotheses'!$D9/12),0) | I28: =if('Costs Hypotheses'!$E9<=I$3,('Costs Hypotheses'!$D9/12),0) | J28: =if('Costs Hypotheses'!$E9<=J$3,('Costs Hypotheses'!$D9/12),0) | ... Z28: =if('Costs Hypotheses'!$E9<=Z$3,('Costs Hypotheses'!$D9/12),0)
B29: =+CONCATENATE('Costs Hypotheses'!B10," - ",'Costs Hypotheses'!C10) | C29: =if('Costs Hypotheses'!$E10<=C$3,('Costs Hypotheses'!$D10/12),0) | D29: =if('Costs Hypotheses'!$E10<=D$3,('Costs Hypotheses'!$D10/12),0) | E29: =if('Costs Hypotheses'!$E10<=E$3,('Costs Hypotheses'!$D10/12),0) | F29: =if('Costs Hypotheses'!$E10<=F$3,('Costs Hypotheses'!$D10/12),0) | G29: =if('Costs Hypotheses'!$E10<=G$3,('Costs Hypotheses'!$D10/12),0) | H29: =if('Costs Hypotheses'!$E10<=H$3,('Costs Hypotheses'!$D10/12),0) | I29: =if('Costs Hypotheses'!$E10<=I$3,('Costs Hypotheses'!$D10/12),0) | J29: =if('Costs Hypotheses'!$E10<=J$3,('Costs Hypotheses'!$D10/12),0) | ... Z29: =if('Costs Hypotheses'!$E10<=Z$3,('Costs Hypotheses'!$D10/12),0)
B30: =+CONCATENATE('Costs Hypotheses'!B11," - ",'Costs Hypotheses'!C11) | C30: =if('Costs Hypotheses'!$E11<=C$3,('Costs Hypotheses'!$D11/12),0) | D30: =if('Costs Hypotheses'!$E11<=D$3,('Costs Hypotheses'!$D11/12),0) | E30: =if('Costs Hypotheses'!$E11<=E$3,('Costs Hypotheses'!$D11/12),0) | F30: =if('Costs Hypotheses'!$E11<=F$3,('Costs Hypotheses'!$D11/12),0) | G30: =if('Costs Hypotheses'!$E11<=G$3,('Costs Hypotheses'!$D11/12),0) | H30: =if('Costs Hypotheses'!$E11<=H$3,('Costs Hypotheses'!$D11/12),0) | I30: =if('Costs Hypotheses'!$E11<=I$3,('Costs Hypotheses'!$D11/12),0) | J30: =if('Costs Hypotheses'!$E11<=J$3,('Costs Hypotheses'!$D11/12),0) | ... Z30: =if('Costs Hypotheses'!$E11<=Z$3,('Costs Hypotheses'!$D11/12),0)
B31: =+CONCATENATE('Costs Hypotheses'!B12," - ",'Costs Hypotheses'!C12) | C31: =if('Costs Hypotheses'!$E12<=C$3,('Costs Hypotheses'!$D12/12),0) | D31: =if('Costs Hypotheses'!$E12<=D$3,('Costs Hypotheses'!$D12/12),0) | E31: =if('Costs Hypotheses'!$E12<=E$3,('Costs Hypotheses'!$D12/12),0) | F31: =if('Costs Hypotheses'!$E12<=F$3,('Costs Hypotheses'!$D12/12),0) | G31: =if('Costs Hypotheses'!$E12<=G$3,('Costs Hypotheses'!$D12/12),0) | H31: =if('Costs Hypotheses'!$E12<=H$3,('Costs Hypotheses'!$D12/12),0) | I31: =if('Costs Hypotheses'!$E12<=I$3,('Costs Hypotheses'!$D12/12),0) | J31: =if('Costs Hypotheses'!$E12<=J$3,('Costs Hypotheses'!$D12/12),0) | ... Z31: =if('Costs Hypotheses'!$E12<=Z$3,('Costs Hypotheses'!$D12/12),0)
B32: =+CONCATENATE('Costs Hypotheses'!B13," - ",'Costs Hypotheses'!C13) | C32: =if('Costs Hypotheses'!$E13<=C$3,('Costs Hypotheses'!$D13/12),0) | D32: =if('Costs Hypotheses'!$E13<=D$3,('Costs Hypotheses'!$D13/12),0) | E32: =if('Costs Hypotheses'!$E13<=E$3,('Costs Hypotheses'!$D13/12),0) | F32: =if('Costs Hypotheses'!$E13<=F$3,('Costs Hypotheses'!$D13/12),0) | G32: =if('Costs Hypotheses'!$E13<=G$3,('Costs Hypotheses'!$D13/12),0) | H32: =if('Costs Hypotheses'!$E13<=H$3,('Costs Hypotheses'!$D13/12),0) | I32: =if('Costs Hypotheses'!$E13<=I$3,('Costs Hypotheses'!$D13/12),0) | J32: =if('Costs Hypotheses'!$E13<=J$3,('Costs Hypotheses'!$D13/12),0) | ... Z32: =if('Costs Hypotheses'!$E13<=Z$3,('Costs Hypotheses'!$D13/12),0)
B33: =+CONCATENATE('Costs Hypotheses'!B14," - ",'Costs Hypotheses'!C14) | C33: =if('Costs Hypotheses'!$E14<=C$3,('Costs Hypotheses'!$D14/12),0) | D33: =if('Costs Hypotheses'!$E14<=D$3,('Costs Hypotheses'!$D14/12),0) | E33: =if('Costs Hypotheses'!$E14<=E$3,('Costs Hypotheses'!$D14/12),0) | F33: =if('Costs Hypotheses'!$E14<=F$3,('Costs Hypotheses'!$D14/12),0) | G33: =if('Costs Hypotheses'!$E14<=G$3,('Costs Hypotheses'!$D14/12),0) | H33: =if('Costs Hypotheses'!$E14<=H$3,('Costs Hypotheses'!$D14/12),0) | I33: =if('Costs Hypotheses'!$E14<=I$3,('Costs Hypotheses'!$D14/12),0) | J33: =if('Costs Hypotheses'!$E14<=J$3,('Costs Hypotheses'!$D14/12),0) | ... Z33: =if('Costs Hypotheses'!$E14<=Z$3,('Costs Hypotheses'!$D14/12),0)
... B41: =+CONCATENATE('Costs Hypotheses'!B22," - ",'Costs Hypotheses'!C22) | C41: =if('Costs Hypotheses'!$E22<=C$3,('Costs Hypotheses'!$D22/12),0) | D41: =if('Costs Hypotheses'!$E22<=D$3,('Costs Hypotheses'!$D22/12),0) | E41: =if('Costs Hypotheses'!$E22<=E$3,('Costs Hypotheses'!$D22/12),0) | F41: =if('Costs Hypotheses'!$E22<=F$3,('Costs Hypotheses'!$D22/12),0) | G41: =if('Costs Hypotheses'!$E22<=G$3,('Costs Hypotheses'!$D22/12),0) | H41: =if('Costs Hypotheses'!$E22<=H$3,('Costs Hypotheses'!$D22/12),0) | I41: =if('Costs Hypotheses'!$E22<=I$3,('Costs Hypotheses'!$D22/12),0) | J41: =if('Costs Hypotheses'!$E22<=J$3,('Costs Hypotheses'!$D22/12),0) | ... Z41: =if('Costs Hypotheses'!$E22<=Z$3,('Costs Hypotheses'!$D22/12),0)
B42: Total Payroll | C42: =sum(C22:C41) | D42: =sum(D22:D41) | E42: =sum(E22:E41) | F42: =sum(F22:F41) | G42: =sum(G22:G41) | H42: =sum(H22:H41) | I42: =sum(I22:I41) | J42: =sum(J22:J41) | ... Z42: =sum(Z22:Z41)
A44: Marketing Spending
B45: ='Costs Hypotheses'!B26 | C45: ='Costs Hypotheses'!$D26*C14 | D45: ='Costs Hypotheses'!$D26*D14 | E45: ='Costs Hypotheses'!$D26*E14 | F45: ='Costs Hypotheses'!$D26*F14 | G45: ='Costs Hypotheses'!$D26*G14 | H45: ='Costs Hypotheses'!$D26*H14 | I45: ='Costs Hypotheses'!$D26*I14 | J45: ='Costs Hypotheses'!$D26*J14 | ... Z45: ='Costs Hypotheses'!$D26*Z14
B46: ='Costs Hypotheses'!B27 | C46: ='Costs Hypotheses'!$D27*C14 | D46: ='Costs Hypotheses'!$D27*D14 | E46: ='Costs Hypotheses'!$D27*E14 | F46: ='Costs Hypotheses'!$D27*F14 | G46: ='Costs Hypotheses'!$D27*G14 | H46: ='Costs Hypotheses'!$D27*H14 | I46: ='Costs Hypotheses'!$D27*I14 | J46: ='Costs Hypotheses'!$D27*J14 | ... Z46: ='Costs Hypotheses'!$D27*Z14
B47: Total Marketing Spending | C47: =sum(C45:C46) | D47: =sum(D45:D46) | E47: =sum(E45:E46) | F47: =sum(F45:F46) | G47: =sum(G45:G46) | H47: =sum(H45:H46) | I47: =sum(I45:I46) | J47: =sum(J45:J46) | ... Z47: =sum(Z45:Z46)
A48: Hosting
B49: ='Costs Hypotheses'!B31 | C49: ='Costs Hypotheses'!$D31 | D49: ='Costs Hypotheses'!$D31 | E49: ='Costs Hypotheses'!$D31 | F49: ='Costs Hypotheses'!$D31 | G49: ='Costs Hypotheses'!$D31 | H49: ='Costs Hypotheses'!$D31 | I49: ='Costs Hypotheses'!$D31 | J49: ='Costs Hypotheses'!$D31 | ... Z49: ='Costs Hypotheses'!$D31
B50: Total Hosting | C50: =C49 | D50: =D49 | E50: =E49 | F50: =F49 | G50: =G49 | H50: =H49 | I50: =I49 | J50: =J49 | ... Z50: =Z49
A51: ='Costs Hypotheses'!A33
B52: ='Costs Hypotheses'!B34 | C52: ='Costs Hypotheses'!$D34 | D52: ='Costs Hypotheses'!$D34 | E52: ='Costs Hypotheses'!$D34 | F52: ='Costs Hypotheses'!$D34 | G52: ='Costs Hypotheses'!$D34 | H52: ='Costs Hypotheses'!$D34 | I52: ='Costs Hypotheses'!$D34 | J52: ='Costs Hypotheses'!$D34 | ... Z52: ='Costs Hypotheses'!$D34
B53: ='Costs Hypotheses'!B35 | C53: ='Costs Hypotheses'!$D35 | D53: ='Costs Hypotheses'!$D35 | E53: ='Costs Hypotheses'!$D35 | F53: ='Costs Hypotheses'!$D35 | G53: ='Costs Hypotheses'!$D35 | H53: ='Costs Hypotheses'!$D35 | I53: ='Costs Hypotheses'!$D35 | J53: ='Costs Hypotheses'!$D35 | ... Z53: ='Costs Hypotheses'!$D35
B54: ='Costs Hypotheses'!B36 | C54: ='Costs Hypotheses'!$D36 | D54: ='Costs Hypotheses'!$D36 | E54: ='Costs Hypotheses'!$D36 | F54: ='Costs Hypotheses'!$D36 | G54: ='Costs Hypotheses'!$D36 | H54: ='Costs Hypotheses'!$D36 | I54: ='Costs Hypotheses'!$D36 | J54: ='Costs Hypotheses'!$D36 | ... Z54: ='Costs Hypotheses'!$D36
B55: ='Costs Hypotheses'!B37 | C55: ='Costs Hypotheses'!$D37 | D55: ='Costs Hypotheses'!$D37 | E55: ='Costs Hypotheses'!$D37 | F55: ='Costs Hypotheses'!$D37 | G55: ='Costs Hypotheses'!$D37 | H55: ='Costs Hypotheses'!$D37 | I55: ='Costs Hypotheses'!$D37 | J55: ='Costs Hypotheses'!$D37 | ... Z55: ='Costs Hypotheses'!$D37
B56: ='Costs Hypotheses'!B38 | C56: ='Costs Hypotheses'!$D38 | D56: ='Costs Hypotheses'!$D38 | E56: ='Costs Hypotheses'!$D38 | F56: ='Costs Hypotheses'!$D38 | G56: ='Costs Hypotheses'!$D38 | H56: ='Costs Hypotheses'!$D38 | I56: ='Costs Hypotheses'!$D38 | J56: ='Costs Hypotheses'!$D38 | ... Z56: ='Costs Hypotheses'!$D38
B57: ='Costs Hypotheses'!B39 | C57: ='Costs Hypotheses'!$D39 | D57: ='Costs Hypotheses'!$D39 | E57: ='Costs Hypotheses'!$D39 | F57: ='Costs Hypotheses'!$D39 | G57: ='Costs Hypotheses'!$D39 | H57: ='Costs Hypotheses'!$D39 | I57: ='Costs Hypotheses'!$D39 | J57: ='Costs Hypotheses'!$D39 | ... Z57: ='Costs Hypotheses'!$D39
B58: ='Costs Hypotheses'!B40 | C58: ='Costs Hypotheses'!$D40 | D58: ='Costs Hypotheses'!$D40 | E58: ='Costs Hypotheses'!$D40 | F58: ='Costs Hypotheses'!$D40 | G58: ='Costs Hypotheses'!$D40 | H58: ='Costs Hypotheses'!$D40 | I58: ='Costs Hypotheses'!$D40 | J58: ='Costs Hypotheses'!$D40 | ... Z58: ='Costs Hypotheses'!$D40
B59: ='Costs Hypotheses'!B41 | C59: ='Costs Hypotheses'!$D41 | D59: ='Costs Hypotheses'!$D41 | E59: ='Costs Hypotheses'!$D41 | F59: ='Costs Hypotheses'!$D41 | G59: ='Costs Hypotheses'!$D41 | H59: ='Costs Hypotheses'!$D41 | I59: ='Costs Hypotheses'!$D41 | J59: ='Costs Hypotheses'!$D41 | ... Z59: ='Costs Hypotheses'!$D41
B60: ='Costs Hypotheses'!B42 | C60: ='Costs Hypotheses'!$D42 | D60: ='Costs Hypotheses'!$D42 | E60: ='Costs Hypotheses'!$D42 | F60: ='Costs Hypotheses'!$D42 | G60: ='Costs Hypotheses'!$D42 | H60: ='Costs Hypotheses'!$D42 | I60: ='Costs Hypotheses'!$D42 | J60: ='Costs Hypotheses'!$D42 | ... Z60: ='Costs Hypotheses'!$D42
B61: Total Miscellaneous | C61: =sum(C52:C60) | D61: =sum(D52:D60) | E61: =sum(E52:E60) | F61: =sum(F52:F60) | G61: =sum(G52:G60) | H61: =sum(H52:H60) | I61: =sum(I52:I60) | J61: =sum(J52:J60) | ... Z61: =sum(Z52:Z60)
A63: PROFIT & LOSS
A65: Revenue
B66: Gross MRR | C66: =C14 | D66: =D14 | E66: =E14 | F66: =F14 | G66: =G14 | H66: =H14 | I66: =I14 | J66: =J14 | ... Z66: =Z14
A67: Costs of Good sold
B68: =B16 | C68: =C16 | D68: =D16 | E68: =E16 | F68: =F16 | G68: =G16 | H68: =H16 | I68: =I16 | ... Z68: =Z16
B69: =B49 | C69: =C49 | D69: =D49 | E69: =E49 | F69: =F49 | G69: =G49 | H69: =H49 | I69: =I49 | ... Z69: =Z49
B70: Support | C70: =sumif('Costs Hypotheses'!$F$3:$F$22,$B$70,C22:C41) | D70: =sumif('Costs Hypotheses'!$F$3:$F$22,$B$70,D22:D41) | E70: =sumif('Costs Hypotheses'!$F$3:$F$22,$B$70,E22:E41) | F70: =sumif('Costs Hypotheses'!$F$3:$F$22,$B$70,F22:F41) | G70: =sumif('Costs Hypotheses'!$F$3:$F$22,$B$70,G22:G41) | H70: =sumif('Costs Hypotheses'!$F$3:$F$22,$B$70,H22:H41) | I70: =sumif('Costs Hypotheses'!$F$3:$F$22,$B$70,I22:I41) | J70: =sumif('Costs Hypotheses'!$F$3:$F$22,$B$70,J22:J41) | ... Z70: =sumif('Costs Hypotheses'!$F$3:$F$22,$B$70,Z22:Z41)
B71: Total Costs of Good Sold | C71: =sum(C68:C70) | D71: =sum(D68:D70) | E71: =sum(E68:E70) | F71: =sum(F68:F70) | G71: =sum(G68:G70) | H71: =sum(H68:H70) | I71: =sum(I68:I70) | J71: =sum(J68:J70) | ... Z71: =sum(Z68:Z70)
C72: =C71/C66 | D72: =D71/D66 | E72: =E71/E66 | F72: =F71/F66 | G72: =G71/G66 | H72: =H71/H66 | I72: =I71/I66 | J72: =J71/J66 | ... Z72: =Z71/Z66
A73: Gross Profit
B74: Gross Profit | C74: =C66-C71 | D74: =D66-D71 | E74: =E66-E71 | F74: =F66-F71 | G74: =G66-G71 | H74: =H66-H71 | I74: =I66-I71 | J74: =J66-J71 | ... Z74: =Z66-Z71
C75: =C74/C66 | D75: =D74/D66 | E75: =E74/E66 | F75: =F74/F66 | G75: =G74/G66 | H75: =H74/H66 | I75: =I74/I66 | J75: =J74/J66 | ... Z75: =Z74/Z66
A76: Operating Expenses
B77: Sales & Marketing | C77: =sumif('Costs Hypotheses'!$F$3:$F$22,$B$77,C22:C41)+C47+C53 | D77: =sumif('Costs Hypotheses'!$F$3:$F$22,$B$77,D22:D41)+D47+D53 | E77: =sumif('Costs Hypotheses'!$F$3:$F$22,$B$77,E22:E41)+E47+E53 | F77: =sumif('Costs Hypotheses'!$F$3:$F$22,$B$77,F22:F41)+F47+F53 | G77: =sumif('Costs Hypotheses'!$F$3:$F$22,$B$77,G22:G41)+G47+G53 | H77: =sumif('Costs Hypotheses'!$F$3:$F$22,$B$77,H22:H41)+H47+H53 | I77: =sumif('Costs Hypotheses'!$F$3:$F$22,$B$77,I22:I41)+I47+I53 | J77: =sumif('Costs Hypotheses'!$F$3:$F$22,$B$77,J22:J41)+J47+J53 | ... Z77: =sumif('Costs Hypotheses'!$F$3:$F$22,$B$77,Z22:Z41)+Z47+Z53
B78: % of Revenues | C78: =C77/C66 | D78: =D77/D66 | E78: =E77/E66 | F78: =F77/F66 | G78: =G77/G66 | H78: =H77/H66 | I78: =I77/I66 | J78: =J77/J66 | ... Z78: =Z77/Z66
B80: Research & Development | C80: =sumif('Costs Hypotheses'!$F$3:$F$22,$B$80,C22:C41)+C52 | D80: =sumif('Costs Hypotheses'!$F$3:$F$22,$B$80,D22:D41)+D52 | E80: =sumif('Costs Hypotheses'!$F$3:$F$22,$B$80,E22:E41)+E52 | F80: =sumif('Costs Hypotheses'!$F$3:$F$22,$B$80,F22:F41)+F52 | G80: =sumif('Costs Hypotheses'!$F$3:$F$22,$B$80,G22:G41)+G52 | H80: =sumif('Costs Hypotheses'!$F$3:$F$22,$B$80,H22:H41)+H52 | I80: =sumif('Costs Hypotheses'!$F$3:$F$22,$B$80,I22:I41)+I52 | J80: =sumif('Costs Hypotheses'!$F$3:$F$22,$B$80,J22:J41)+J52 | ... Z80: =sumif('Costs Hypotheses'!$F$3:$F$22,$B$80,Z22:Z41)+Z52
B81: % of Revenues | C81: =C80/C66 | D81: =D80/D66 | E81: =E80/E66 | F81: =F80/F66 | G81: =G80/G66 | H81: =H80/H66 | I81: =I80/I66 | J81: =J80/J66 | ... Z81: =Z80/Z66
B83: General & Administrative | C83: =sumif('Costs Hypotheses'!$F$3:$F$22,$B$83,C22:C41)+sum(C54:C60) | D83: =sumif('Costs Hypotheses'!$F$3:$F$22,$B$83,D22:D41)+sum(D54:D60) | E83: =sumif('Costs Hypotheses'!$F$3:$F$22,$B$83,E22:E41)+sum(E54:E60) | F83: =sumif('Costs Hypotheses'!$F$3:$F$22,$B$83,F22:F41)+sum(F54:F60) | G83: =sumif('Costs Hypotheses'!$F$3:$F$22,$B$83,G22:G41)+sum(G54:G60) | H83: =sumif('Costs Hypotheses'!$F$3:$F$22,$B$83,H22:H41)+sum(H54:H60) | I83: =sumif('Costs Hypotheses'!$F$3:$F$22,$B$83,I22:I41)+sum(I54:I60) | J83: =sumif('Costs Hypotheses'!$F$3:$F$22,$B$83,J22:J41)+sum(J54:J60) | ... Z83: =sumif('Costs Hypotheses'!$F$3:$F$22,$B$83,Z22:Z41)+sum(Z54:Z60)
B84: % of Revenues | C84: =C83/C66 | D84: =D83/D66 | E84: =E83/E66 | F84: =F83/F66 | G84: =G83/G66 | H84: =H83/H66 | I84: =I83/I66 | J84: =J83/J66 | ... Z84: =Z83/Z66
A86: Margins
B87: Earning Before Interest & Tax | C87: =C74-C77-C80-C83 | D87: =D74-D77-D80-D83 | E87: =E74-E77-E80-E83 | F87: =F74-F77-F80-F83 | G87: =G74-G77-G80-G83 | H87: =H74-H77-H80-H83 | I87: =I74-I77-I80-I83 | J87: =J74-J77-J80-J83 | ... Z87: =Z74-Z77-Z80-Z83
B88: EBIT Margin | C88: =C87/C66 | D88: =D87/D66 | E88: =E87/E66 | F88: =F87/F66 | G88: =G87/G66 | H88: =H87/H66 | I88: =I87/I66 | J88: =J87/J66 | ... Z88: =Z87/Z66

Sheet Base Case P&L
A1: GuardSpine SaaS P&L -- Base Case
A2: Generated: Feb 18, 2026 | $1M raise at $9M pre / $10M post
A4: Metric | B4: Year 1 | N4: Year 2 | Z4: Y1 Total | AA4: Y2 Total
A5: Month | B5: Jan-2026 | C5: Feb-2026 | D5: Mar-2026 | E5: Apr-2026 | F5: May-2026 | G5: Jun-2026 | H5: Jul-2026 | I5: Aug-2026 | J5: Sep-2026 | K5: Oct-2026 | L5: Nov-2026 | M5: Dec-2026 | N5: Jan-2027 | O5: Feb-2027 | P5: Mar-2027 | Q5: Apr-2027 | R5: May-2027 | S5: Jun-2027 | T5: Jul-2027 | U5: Aug-2027 | V5: Sep-2027 | W5: Oct-2027 | X5: Nov-2027 | Y5: Dec-2027
A6: Month # | B6: 1 | C6: 2 | D6: 3 | E6: 4 | F6: 5 | G6: 6 | H6: 7 | I6: 8 | J6: 9 | K6: 10 | L6: 11 | M6: 12 | N6: 13 | O6: 14 | P6: 15 | Q6: 16 | R6: 17 | S6: 18 | T6: 19 | U6: 20 | V6: 21 | W6: 22 | X6: 23 | Y6: 24
A8: REVENUE
A9: Avg Price / Customer | B9: 2500 | C9: 2500 | D9: 2500 | E9: 2500 | F9: 2500 | G9: 2500 | H9: 2500 | I9: 2500 | J9: 2500 | K9: 2500 | L9: 2500 | M9: 2500 | N9: 2900 | O9: 2900 | P9: 2900 | Q9: 2900 | R9: 2900 | S9: 2900 | T9: 2900 | U9: 2900 | V9: 2900 | W9: 2900 | X9: 2900 | Y9: 2900
A10: Customers | B10: 2 | C10: 3 | D10: 5 | E10: 7 | F10: 9 | G10: 11 | H10: 13 | I10: 16 | J10: 18 | K10: 21 | L10: 25 | M10: 28 | N10: 27 | O10: 31 | P10: 35 | Q10: 39 | R10: 43 | S10: 48 | T10: 52 | U10: 58 | V10: 63 | W10: 69 | X10: 75 | Y10: 81
A11: New Customers | B11: 1 | C11: 1 | D11: 2 | E11: 2 | F11: 2 | G11: 2 | H11: 2 | I11: 3 | J11: 2 | K11: 3 | L11: 4 | M11: 3 | N11: 0 | O11: 4 | P11: 4 | Q11: 4 | R11: 4 | S11: 5 | T11: 4 | U11: 6 | V11: 5 | W11: 6 | X11: 6 | Y11: 6
A12: Gross MRR | B12: 5367.5 | C12: 8657.6475 | D12: 12433.862 | E12: 16655.01 | F12: 21374.509 | G12: 26652.186 | H12: 32421.556 | I12: 38755.448 | J12: 45710.361 | K12: 53206.25 | L12: 61286.454 | M12: 69997.779 | N12: 79390.776 | O12: 89520.041 | P12: 100444.53 | Q12: 112115.11 | R12: 124584.07 | S12: 137907.37 | T12: 152006.68 | U12: 166928.64 | V12: 182722.72 | W12: 199276.71 | X12: 216628.73 | Y12: 234818.8 | Z12: 392518.56 | AA12: 1796344.2
A13: Lost MRR (Churn) | B13: 7.5 | C13: 16.1025 | D13: 25.972942 | E13: 37.301586 | F13: 49.965031 | G13: 64.123528 | H13: 106.60874 | I13: 129.68623 | J13: 155.02179 | K13: 182.84145 | L13: 212.825 | M13: 245.14582 | N13: 279.99112 | O13: 317.56311 | P13: 358.08016 | Q13: 401.77814 | R13: 448.46044 | S13: 498.33628 | T13: 551.62948 | U13: 608.02671 | V13: 667.71458 | W13: 730.89089 | X13: 797.10685 | Y13: 866.51493
A14: Net MRR | B14: 5360 | C14: 8641.545 | D14: 12407.889 | E14: 16617.709 | F14: 21324.544 | G14: 26588.062 | H14: 32314.948 | I14: 38625.762 | J14: 45555.34 | K14: 53023.409 | L14: 61073.629 | M14: 69752.633 | N14: 79110.785 | O14: 89202.478 | P14: 100086.45 | Q14: 111713.33 | R14: 124135.61 | S14: 137409.03 | T14: 151455.05 | U14: 166320.62 | V14: 182055.01 | W14: 198545.82 | X14: 215831.62 | Y14: 233952.28
A15: ARR (MRR x 12) | B15: 64410 | C15: 103891.77 | D15: 149206.34 | E15: 199860.13 | F15: 256494.11 | G15: 319826.23 | H15: 389058.68 | I15: 465065.37 | J15: 548524.34 | K15: 638475 | L15: 735437.45 | M15: 839973.35 | N15: 952689.32 | O15: 1074240.5 | P15: 1205334.4 | Q15: 1345381.3 | R15: 1495008.8 | S15: 1654888.5 | T15: 1824080.1 | U15: 2003143.7 | V15: 2192672.7 | W15: 2391320.5 | X15: 2599544.8 | Y15: 2817825.6
A16: MRR Growth Rate | B16: 0 | C16: 0.61297578 | D16: 0.43617098 | E16: 0.33948812 | F16: 0.28336812 | G16: 0.24691449 | H16: 0.21646896 | I16: 0.1953605 | J16: 0.17945641 | K16: 0.16398664 | L16: 0.15186568 | M16: 0.14214112 | N16: 0.13418994 | O16: 0.12758742 | P16: 0.12203406 | Q16: 0.11618926 | R16: 0.11121568 | S16: 0.10694226 | T16: 0.10223752 | U16: 0.098166516 | V16: 0.094615743 | W16: 0.090596237 | X16: 0.087074997 | Y16: 0.083968858
A18: COST OF GOODS SOLD
A19: Payment Processing (3%) | B19: 161.025 | C19: 259.72942 | D19: 373.01586 | E19: 499.65031 | F19: 641.23528 | G19: 799.56557 | H19: 972.64669 | I19: 1162.6634 | J19: 1371.3108 | K19: 1596.1875 | L19: 1838.5936 | M19: 2099.9334 | N19: 2381.7233 | O19: 2685.6012 | P19: 3013.336 | Q19: 3363.4533 | R19: 3737.5221 | S19: 4137.2211 | T19: 4560.2003 | U19: 5007.8593 | V19: 5481.6816 | W19: 5978.3014 | X19: 6498.8619 | Y19: 7044.564
A20: Hosting & Bandwidth | B20: 1500 | C20: 1500 | D20: 1500 | E20: 1500 | F20: 1500 | G20: 1500 | H20: 1500 | I20: 1500 | J20: 1500 | K20: 1500 | L20: 1500 | M20: 1500 | N20: 1500 | O20: 1500 | P20: 1500 | Q20: 1500 | R20: 1500 | S20: 1500 | T20: 1500 | U20: 1500 | V20: 1500 | W20: 1500 | X20: 1500 | Y20: 1500
A21: Total COGS | B21: 1661.025 | C21: 1759.7294 | D21: 1873.0159 | E21: 1999.6503 | F21: 2141.2353 | G21: 2299.5656 | H21: 2472.6467 | I21: 2662.6634 | J21: 2871.3108 | K21: 3096.1875 | L21: 3338.5936 | M21: 3599.9334 | N21: 3881.7233 | O21: 4185.6012 | P21: 4513.336 | Q21: 4863.4533 | R21: 5237.5221 | S21: 5637.2211 | T21: 6060.2003 | U21: 6507.8593 | V21: 6981.6816 | W21: 7478.3014 | X21: 7998.8619 | Y21: 8544.564 | Z21: 29775.557 | AA21: 71890.326
A22: COGS % of Revenue | B22: 0.30945971 | C22: 0.20325723 | D22: 0.1506383 | E22: 0.12006299 | F22: 0.10017705 | G22: 0.086280563 | H22: 0.076265515 | I22: 0.068704236 | J22: 0.062815317 | K22: 0.058192177 | L22: 0.054475229 | M22: 0.051429251 | N22: 0.048893882 | O22: 0.046756025 | P22: 0.044933615 | Q22: 0.043379106 | R22: 0.042040063 | S22: 0.040876866 | T22: 0.039867988 | U22: 0.038985875 | V22: 0.03820916 | W22: 0.037527222 | X22: 0.036924289 | Y22: 0.036387904
A24: GROSS PROFIT
A25: Gross Profit | B25: 3706.475 | C25: 6897.9181 | D25: 10560.846 | E25: 14655.36 | F25: 19233.274 | G25: 24352.62 | H25: 29948.91 | I25: 36092.784 | J25: 42839.051 | K25: 50110.063 | L25: 57947.86 | M25: 66397.846 | N25: 75509.053 | O25: 85334.44 | P25: 95931.199 | Q25: 107251.66 | R25: 119346.55 | S25: 132270.15 | T25: 145946.48 | U25: 160420.78 | V25: 175741.04 | W25: 191798.41 | X25: 208629.87 | Y25: 226274.23
A26: Gross Margin % | B26: 0.69054029 | C26: 0.79674277 | D26: 0.8493617 | E26: 0.87993701 | F26: 0.89982295 | G26: 0.91371944 | H26: 0.92373449 | I26: 0.93129576 | J26: 0.93718468 | K26: 0.94180782 | L26: 0.94552477 | M26: 0.94857075 | N26: 0.95110612 | O26: 0.95324398 | P26: 0.95506639 | Q26: 0.95662089 | R26: 0.95795994 | S26: 0.95912313 | T26: 0.96013201 | U26: 0.96101412 | V26: 0.96179084 | W26: 0.96247278 | X26: 0.96307571 | Y26: 0.9636121
A28: PERSONNEL
A29: CEO - David Youssef (G&A) | B29: 10000 | C29: 10000 | D29: 10000 | E29: 10000 | F29: 10000 | G29: 10000 | H29: 10000 | I29: 10000 | J29: 10000 | K29: 10000 | L29: 10000 | M29: 10000 | N29: 10000 | O29: 10000 | P29: 10000 | Q29: 10000 | R29: 10000 | S29: 10000 | T29: 10000 | U29: 10000 | V29: 10000 | W29: 10000 | X29: 10000 | Y29: 10000
A30: CTO - Igor Malovitsa (R&D) | B30: 10000 | C30: 10000 | D30: 10000 | E30: 10000 | F30: 10000 | G30: 10000 | H30: 10000 | I30: 10000 | J30: 10000 | K30: 10000 | L30: 10000 | M30: 10000 | N30: 10000 | O30: 10000 | P30: 10000 | Q30: 10000 | R30: 10000 | S30: 10000 | T30: 10000 | U30: 10000 | V30: 10000 | W30: 10000 | X30: 10000 | Y30: 10000
A31: GTM - Kristen Hengst Smith (S&M) | B31: 7000 | C31: 7000 | D31: 7000 | E31: 7000 | F31: 7000 | G31: 7000 | H31: 7000 | I31: 7000 | J31: 7000 | K31: 7000 | L31: 7000 | M31: 7000 | N31: 7000 | O31: 7000 | P31: 7000 | Q31: 7000 | R31: 7000 | S31: 7000 | T31: 7000 | U31: 7000 | V31: 7000 | W31: 7000 | X31: 7000 | Y31: 7000
A32: Engineer - Hire #1 (R&D) | B32: 0 | C32: 0 | D32: 0 | E32: 10000 | F32: 10000 | G32: 10000 | H32: 10000 | I32: 10000 | J32: 10000 | K32: 10000 | L32: 10000 | M32: 10000 | N32: 10000 | O32: 10000 | P32: 10000 | Q32: 10000 | R32: 10000 | S32: 10000 | T32: 10000 | U32: 10000 | V32: 10000 | W32: 10000 | X32: 10000 | Y32: 10000
A33: Engineer - Hire #2 (R&D) | B33: 0 | C33: 0 | D33: 0 | E33: 0 | F33: 0 | G33: 0 | H33: 0 | I33: 0 | J33: 0 | K33: 10000 | L33: 10000 | M33: 10000 | N33: 10000 | O33: 10000 | P33: 10000 | Q33: 10000 | R33: 10000 | S33: 10000 | T33: 10000 | U33: 10000 | V33: 10000 | W33: 10000 | X33: 10000 | Y33: 10000
A34: Total Payroll | B34: 27000 | C34: 27000 | D34: 27000 | E34: 37000 | F34: 37000 | G34: 37000 | H34: 37000 | I34: 37000 | J34: 37000 | K34: 47000 | L34: 47000 | M34: 47000 | N34: 47000 | O34: 47000 | P34: 47000 | Q34: 47000 | R34: 47000 | S34: 47000 | T34: 47000 | U34: 47000 | V34: 47000 | W34: 47000 | X34: 47000 | Y34: 47000 | Z34: 444000 | AA34: 564000
A36: OPERATING EXPENSES
A37: Sales & Marketing | B37: 7322.05 | C37: 7519.4588 | D37: 7746.0317 | E37: 7999.3006 | F37: 8282.4706 | G37: 8599.1311 | H37: 8945.2934 | I37: 9325.3269 | J37: 9742.6217 | K37: 10192.375 | L37: 10677.187 | M37: 11199.867 | N37: 11763.447 | O37: 12371.202 | P37: 13026.672 | Q37: 13726.907 | R37: 14475.044 | S37: 15274.442 | T37: 16120.401 | U37: 17015.719 | V37: 17963.363 | W37: 18956.603 | X37: 19997.724 | Y37: 21089.128 | Z37: 107551.11 | AA37: 191780.65
A38: S&M % of Revenue | B38: 1.3641453 | C38: 0.86853373 | D38: 0.62297874 | E38: 0.48029394 | F38: 0.3874929 | G38: 0.32264263 | H38: 0.27590574 | I38: 0.24061977 | J38: 0.21313815 | K38: 0.19156349 | L38: 0.17421774 | M38: 0.16000317 | N38: 0.14817145 | O38: 0.13819478 | P38: 0.1296902 | Q38: 0.12243583 | R38: 0.11618696 | S38: 0.11075871 | T38: 0.10605061 | U38: 0.10193409 | V38: 0.098309412 | W38: 0.095127035 | X38: 0.09231335 | Y38: 0.08981022
A39: Research & Development | B39: 13000 | C39: 13000 | D39: 13000 | E39: 23000 | F39: 23000 | G39: 23000 | H39: 23000 | I39: 23000 | J39: 23000 | K39: 33000 | L39: 33000 | M39: 33000 | N39: 33000 | O39: 33000 | P39: 33000 | Q39: 33000 | R39: 33000 | S39: 33000 | T39: 33000 | U39: 33000 | V39: 33000 | W39: 33000 | X39: 33000 | Y39: 33000 | Z39: 276000 | AA39: 396000
A40: R&D % of Revenue | B40: 2.4219842 | C40: 1.5015626 | D40: 1.0455319 | E40: 1.3809658 | F40: 1.0760481 | G40: 0.86296863 | H40: 0.70940456 | I40: 0.59346495 | J40: 0.50316819 | K40: 0.62022788 | L40: 0.53845504 | M40: 0.47144353 | N40: 0.41566541 | O40: 0.36863254 | P40: 0.32853953 | Q40: 0.29434034 | R40: 0.26488138 | S40: 0.23929105 | T40: 0.21709573 | U40: 0.19768926 | V40: 0.18060151 | W40: 0.16559888 | X40: 0.15233436 | Y40: 0.14053389
A41: General & Administrative | B41: 14867 | C41: 14867 | D41: 14867 | E41: 14867 | F41: 14867 | G41: 14867 | H41: 14867 | I41: 14867 | J41: 14867 | K41: 14867 | L41: 14867 | M41: 14867 | N41: 14867 | O41: 14867 | P41: 14867 | Q41: 14867 | R41: 14867 | S41: 14867 | T41: 14867 | U41: 14867 | V41: 14867 | W41: 14867 | X41: 14867 | Y41: 14867 | Z41: 178404 | AA41: 178404
A42: G&A % of Revenue | B42: 2.7698184 | C42: 1.7172101 | D42: 1.1956864 | E42: 0.89264429 | F42: 0.69554813 | G42: 0.55781542 | H42: 0.45855294 | I42: 0.38361058 | J42: 0.32524354 | K42: 0.27942206 | L42: 0.24258215 | M42: 0.21239245 | N42: 0.18726357 | O42: 0.16607454 | P42: 0.14801204 | Q42: 0.13260478 | R42: 0.11933307 | S42: 0.10780425 | T42: 0.097804914 | U42: 0.089062007 | V42: 0.081363718 | W42: 0.074604804 | X42: 0.068628939 | Y42: 0.063312648
A43: Total OpEx | B43: 35189.05 | C43: 35386.459 | D43: 35613.032 | E43: 45866.301 | F43: 46149.471 | G43: 46466.131 | H43: 46812.293 | I43: 47192.327 | J43: 47609.622 | K43: 58059.375 | L43: 58544.187 | M43: 59066.867 | N43: 59630.447 | O43: 60238.202 | P43: 60893.672 | Q43: 61593.907 | R43: 62342.044 | S43: 63141.442 | T43: 63987.401 | U43: 64882.719 | V43: 65830.363 | W43: 66823.603 | X43: 67864.724 | Y43: 68956.128 | Z43: 561955.11 | AA43: 766184.65
A45: EBITDA / OPERATING INCOME
A46: EBITDA | B46: -31482.575 | C46: -28488.541 | D46: -25052.186 | E46: -31210.94 | F46: -26916.196 | G46: -22113.511 | H46: -16863.384 | I46: -11099.542 | J46: -4770.5711 | K46: -7949.3123 | L46: -596.327 | M46: 7330.9788 | N46: 15878.607 | O46: 25096.237 | P46: 35037.527 | Q46: 45657.751 | R46: 57004.503 | S46: 69128.708 | T46: 81959.077 | U46: 95538.066 | V46: 109910.68 | W46: 124974.81 | X46: 140765.15 | Y46: 157318.11 | Z46: -199212.11 | AA46: 958269.21
A47: EBITDA Margin % | B47: -5.8654075 | C47: -3.2905637 | D47: -2.0148354 | E47: -1.873967 | F47: -1.2592662 | G47: -0.82970723 | H47: -0.52012875 | I47: -0.28639954 | J47: -0.1043652 | K47: -0.14940561 | L47: -0.00973016 | M47: 0.10473159 | N47: 0.20000568 | O47: 0.28034211 | P47: 0.34882462 | Q47: 0.40723994 | R47: 0.45755852 | S47: 0.50126913 | T47: 0.53918076 | U47: 0.57232877 | V47: 0.6015162 | W47: 0.62714206 | X47: 0.64979906 | Y47: 0.66995533
A49: SaaS OPERATING METRICS
A50: CAC (S&M / New Customers) | B50: 7322.05 | C50: 7519.4588 | D50: 3873.0159 | E50: 3999.6503 | F50: 4141.2353 | G50: 4299.5656 | H50: 4472.6467 | I50: 3108.4423 | J50: 4871.3108 | K50: 3397.4583 | L50: 2669.2968 | M50: 3733.2889 | N50: 0 | O50: 3092.8006 | P50: 3256.668 | Q50: 3431.7267 | R50: 3618.761 | S50: 3054.8885 | T50: 4030.1002 | U50: 2835.9531 | V50: 3592.6727 | W50: 3159.4338 | X50: 3332.954 | Y50: 3514.8547
A51: CAC Payback (months) | B51: 4.2413456 | C51: 3.7750999 | D51: 1.8239654 | E51: 1.818153 | F51: 1.8409112 | G51: 1.8822257 | H51: 1.9367672 | I51: 1.3351042 | J51: 2.0791252 | K51: 1.4429518 | L51: 1.129234 | M51: 1.5742796 | N51: 0 | O51: 1.1187933 | P51: 1.1758229 | Q51: 1.2370146 | R51: 1.3026105 | S51: 1.0983051 | T51: 1.4473944 | U51: 1.0175864 | V51: 1.2880687 | W51: 1.1319384 | X51: 1.1933584 | Y51: 1.2577871
A52: LTV (margin-weighted) | B52: 575450.24 | C52: 663952.31 | D52: 707801.42 | E52: 733280.84 | F52: 749852.46 | G52: 761432.86 | H52: 577334.05 | I52: 582059.85 | J52: 585740.43 | K52: 588629.89 | L52: 590952.98 | M52: 592856.72 | N52: 689551.94 | O52: 691101.88 | P52: 692423.13 | Q52: 693550.15 | R52: 694520.95 | S52: 695364.27 | T52: 696095.71 | U52: 696735.24 | V52: 697298.36 | W52: 697792.76 | X52: 698229.89 | Y52: 698618.77
A53: LTV:CAC Ratio | B53: 78.591411 | C53: 88.297885 | D53: 182.75201 | E53: 183.33624 | F53: 181.06976 | G53: 177.0953 | H53: 129.08108 | I53: 187.2513 | J53: 120.24288 | K53: 173.25596 | L53: 221.38901 | M53: 158.8028 | N53: 0 | O53: 223.45504 | P53: 212.61704 | Q53: 202.09947 | R53: 191.9223 | S53: 227.62346 | T53: 172.72417 | U53: 245.67939 | V53: 194.08903 | W53: 220.86007 | X53: 209.49281 | Y53: 198.76178
A54: Net Revenue Retention | B54: 1 | C54: 1.6129758 | D54: 1.436171 | E54: 1.3394881 | F54: 1.2833681 | G54: 1.2469145 | H54: 1.216469 | I54: 1.1953605 | J54: 1.1794564 | K54: 1.1639866 | L54: 1.1518657 | M54: 1.1421411 | N54: 1.1341899 | O54: 1.1275874 | P54: 1.1220341 | Q54: 1.1161893 | R54: 1.1112157 | S54: 1.1069423 | T54: 1.1022375 | U54: 1.0981665 | V54: 1.0946157 | W54: 1.0905962 | X54: 1.087075 | Y54: 1.0839689
A55: Gross Revenue Retention | B55: 0.997 | C55: 0.997 | D55: 0.997 | E55: 0.997 | F55: 0.997 | G55: 0.997 | H55: 0.996 | I55: 0.996 | J55: 0.996 | K55: 0.996 | L55: 0.996 | M55: 0.996 | N55: 0.996 | O55: 0.996 | P55: 0.996 | Q55: 0.996 | R55: 0.996 | S55: 0.996 | T55: 0.996 | U55: 0.996 | V55: 0.996 | W55: 0.996 | X55: 0.996 | Y55: 0.996
A56: Rule of 40 | B56: -5.8654075 | C56: 4.0651456 | D56: 3.2192163 | E56: 2.1998904 | F56: 2.1411513 | G56: 2.1332667 | H56: 2.0774988 | I56: 2.0579264 | J56: 2.0491117 | K56: 1.8184341 | L56: 1.8126581 | M56: 1.810425 | N56: 1.8102849 | O56: 1.8113912 | P56: 1.8132333 | Q56: 1.801511 | R56: 1.7921467 | S56: 1.7845762 | T56: 1.766031 | U56: 1.750327 | V56: 1.7369051 | W56: 1.7142969 | X56: 1.694699 | Y56: 1.6775816
A58: CASH & RUNWAY ($1M Raise)
A59: Monthly Burn (neg=profit) | B59: 31482.575 | C59: 28488.541 | D59: 25052.186 | E59: 31210.94 | F59: 26916.196 | G59: 22113.511 | H59: 16863.384 | I59: 11099.542 | J59: 4770.5711 | K59: 7949.3123 | L59: 596.327 | M59: -7330.9788 | N59: -15878.607 | O59: -25096.237 | P59: -35037.527 | Q59: -45657.751 | R59: -57004.503 | S59: -69128.708 | T59: -81959.077 | U59: -95538.066 | V59: -109910.68 | W59: -124974.81 | X59: -140765.15 | Y59: -157318.11
A60: Cumulative Cash | B60: 968517.43 | C60: 940028.88 | D60: 914976.7 | E60: 883765.76 | F60: 856849.56 | G60: 834736.05 | H60: 817872.67 | I60: 806773.12 | J60: 802002.55 | K60: 794053.24 | L60: 793456.91 | M60: 800787.89 | N60: 816666.5 | O60: 841762.74 | P60: 876800.26 | Q60: 922458.01 | R60: 979462.52 | S60: 1048591.2 | T60: 1130550.3 | U60: 1226088.4 | V60: 1335999 | W60: 1460973.9 | X60: 1601739 | Y60: 1759057.1
A61: Runway (months) | B61: 30.763603 | C61: 32.996737 | D61: 36.522829 | E61: 28.315896 | F61: 31.833976 | G61: 37.747784 | H61: 48.499915 | I61: 72.68526 | J61: 168.11458 | K61: 99.889552 | L61: 1330.5735 | M61: 99 | N61: 99 | O61: 99 | P61: 99 | Q61: 99 | R61: 99 | S61: 99 | T61: 99 | U61: 99 | V61: 99 | W61: 99 | X61: 99 | Y61: 99
A63: EBITDA Breakeven: Month 12 (Dec-2026)

Sheet Bear Case P&L
A1: GuardSpine SaaS P&L -- Bear Case (Slow Adoption)
A2: Generated: Feb 18, 2026 | $1M raise at $9M pre / $10M post
A4: Metric | B4: Year 1 | N4: Year 2 | Z4: Y1 Total | AA4: Y2 Total
A5: Month | B5: Jan-2026 | C5: Feb-2026 | D5: Mar-2026 | E5: Apr-2026 | F5: May-2026 | G5: Jun-2026 | H5: Jul-2026 | I5: Aug-2026 | J5: Sep-2026 | K5: Oct-2026 | L5: Nov-2026 | M5: Dec-2026 | N5: Jan-2027 | O5: Feb-2027 | P5: Mar-2027 | Q5: Apr-2027 | R5: May-2027 | S5: Jun-2027 | T5: Jul-2027 | U5: Aug-2027 | V5: Sep-2027 | W5: Oct-2027 | X5: Nov-2027 | Y5: Dec-2027
A6: Month # | B6: 1 | C6: 2 | D6: 3 | E6: 4 | F6: 5 | G6: 6 | H6: 7 | I6: 8 | J6: 9 | K6: 10 | L6: 11 | M6: 12 | N6: 13 | O6: 14 | P6: 15 | Q6: 16 | R6: 17 | S6: 18 | T6: 19 | U6: 20 | V6: 21 | W6: 22 | X6: 23 | Y6: 24
A8: REVENUE
A9: Avg Price / Customer | B9: 2000 | C9: 2000 | D9: 2000 | E9: 2000 | F9: 2000 | G9: 2000 | H9: 2000 | I9: 2000 | J9: 2000 | K9: 2000 | L9: 2000 | M9: 2000 | N9: 2200 | O9: 2200 | P9: 2200 | Q9: 2200 | R9: 2200 | S9: 2200 | T9: 2200 | U9: 2200 | V9: 2200 | W9: 2200 | X9: 2200 | Y9: 2200
A10: Customers | B10: 2 | C10: 3 | D10: 5 | E10: 6 | F10: 8 | G10: 9 | H10: 11 | I10: 13 | J10: 15 | K10: 17 | L10: 19 | M10: 21 | N10: 21 | O10: 23 | P10: 26 | Q10: 28 | R10: 30 | S10: 33 | T10: 36 | U10: 38 | V10: 41 | W10: 44 | X10: 47 | Y10: 50
A11: New Customers | B11: 1 | C11: 1 | D11: 2 | E11: 1 | F11: 2 | G11: 1 | H11: 2 | I11: 2 | J11: 2 | K11: 2 | L11: 2 | M11: 2 | N11: 0 | O11: 2 | P11: 3 | Q11: 2 | R11: 2 | S11: 3 | T11: 3 | U11: 2 | V11: 3 | W11: 3 | X11: 3 | Y11: 3
A12: Gross MRR | B12: 4190 | C12: 6589.05 | D12: 9218.1047 | E12: 12046.974 | F12: 15091.696 | G12: 18369.591 | H12: 21813.928 | I12: 25450.872 | J12: 29292.065 | K12: 33309.904 | L12: 37513.317 | M12: 41911.673 | N12: 46514.81 | O12: 51333.059 | P12: 56377.265 | Q12: 61605.294 | R12: 67024.607 | S12: 72642.962 | T12: 78468.426 | U12: 84509.391 | V12: 90774.581 | W12: 97205.347 | X12: 103806.79 | Y12: 110584.17 | Z12: 254797.18 | AA12: 920846.7
A13: Lost MRR (Churn) | B13: 10 | C13: 20.95 | D13: 32.94525 | E13: 46.090524 | F13: 60.234871 | G13: 75.458481 | H13: 110.21755 | I13: 130.88357 | J13: 152.70523 | K13: 175.75239 | L13: 199.85943 | M13: 225.0799 | N13: 251.47004 | O13: 279.08886 | P13: 307.99835 | Q13: 338.26359 | R13: 369.63177 | S13: 402.14764 | T13: 435.85777 | U13: 470.81056 | V13: 507.05635 | W13: 544.64749 | X13: 583.23208 | Y13: 622.84075
A14: Net MRR | B14: 4180 | C14: 6568.1 | D14: 9185.1595 | E14: 12000.884 | F14: 15031.461 | G14: 18294.133 | H14: 21703.71 | I14: 25319.989 | J14: 29139.359 | K14: 33134.152 | L14: 37313.458 | M14: 41686.593 | N14: 46263.34 | O14: 51053.97 | P14: 56069.267 | Q14: 61267.031 | R14: 66654.975 | S14: 72240.814 | T14: 78032.569 | U14: 84038.581 | V14: 90267.525 | W14: 96660.7 | X14: 103223.56 | Y14: 109961.33
A15: ARR (MRR x 12) | B15: 50280 | C15: 79068.6 | D15: 110617.26 | E15: 144563.69 | F15: 181100.35 | G15: 220435.09 | H15: 261767.14 | I15: 305410.47 | J15: 351504.77 | K15: 399718.85 | L15: 450159.8 | M15: 502940.07 | N15: 558177.72 | O15: 615996.71 | P15: 676527.18 | Q15: 739263.53 | R15: 804295.29 | S15: 871715.54 | T15: 941621.12 | U15: 1014112.7 | V15: 1089295 | W15: 1166464.2 | X15: 1245681.5 | Y15: 1327010
A16: MRR Growth Rate | B16: 0 | C16: 0.57256563 | D16: 0.39900361 | E16: 0.3068819 | F16: 0.25273748 | G16: 0.21719857 | H16: 0.18750211 | I16: 0.16672578 | J16: 0.15092576 | K16: 0.13716479 | L16: 0.12619107 | M16: 0.11724785 | N16: 0.10982948 | O16: 0.10358526 | P16: 0.098264284 | Q16: 0.092732934 | R16: 0.087968296 | S16: 0.083825253 | T16: 0.080193104 | U16: 0.076985929 | V16: 0.07413602 | W16: 0.070843248 | X16: 0.067912355 | Y16: 0.065288364
A18: COST OF GOODS SOLD
A19: Payment Processing (3%) | B19: 125.7 | C19: 197.6715 | D19: 276.54314 | E19: 361.40923 | F19: 452.75088 | G19: 551.08773 | H19: 654.41784 | I19: 763.52617 | J19: 878.76194 | K19: 999.29713 | L19: 1125.3995 | M19: 1257.3502 | N19: 1395.4443 | O19: 1539.9918 | P19: 1691.318 | Q19: 1848.1588 | R19: 2010.7382 | S19: 2179.2889 | T19: 2354.0528 | U19: 2535.2817 | V19: 2723.2374 | W19: 2916.1604 | X19: 3114.2037 | Y19: 3317.525
A20: Hosting & Bandwidth | B20: 1500 | C20: 1500 | D20: 1500 | E20: 1500 | F20: 1500 | G20: 1500 | H20: 1500 | I20: 1500 | J20: 1500 | K20: 1500 | L20: 1500 | M20: 1500 | N20: 1500 | O20: 1500 | P20: 1500 | Q20: 1500 | R20: 1500 | S20: 1500 | T20: 1500 | U20: 1500 | V20: 1500 | W20: 1500 | X20: 1500 | Y20: 1500
A21: Total COGS | B21: 1625.7 | C21: 1697.6715 | D21: 1776.5431 | E21: 1861.4092 | F21: 1952.7509 | G21: 2051.0877 | H21: 2154.4178 | I21: 2263.5262 | J21: 2378.7619 | K21: 2499.2971 | L21: 2625.3995 | M21: 2757.3502 | N21: 2895.4443 | O21: 3039.9918 | P21: 3191.318 | Q21: 3348.1588 | R21: 3510.7382 | S21: 3679.2889 | T21: 3854.0528 | U21: 4035.2817 | V21: 4223.2374 | W21: 4416.1604 | X21: 4614.2037 | Y21: 4817.525 | Z21: 25643.915 | AA21: 45625.401
A22: COGS % of Revenue | B22: 0.38799523 | C22: 0.25765042 | D22: 0.19272325 | E22: 0.15451259 | F22: 0.12939241 | G22: 0.11165669 | H22: 0.098763407 | I22: 0.088937076 | J22: 0.081208408 | K22: 0.075031651 | L22: 0.0699858 | M22: 0.065789552 | N22: 0.062247794 | O22: 0.059220935 | P22: 0.05660647 | Q22: 0.054348557 | R22: 0.05237984 | S22: 0.050648938 | T22: 0.049115969 | U22: 0.047749507 | V22: 0.04652445 | W22: 0.04543125 | X22: 0.044449922 | Y22: 0.043564329
A24: GROSS PROFIT
A25: Gross Profit | B25: 2564.3 | C25: 4891.3785 | D25: 7441.5616 | E25: 10185.565 | F25: 13138.945 | G25: 16318.503 | H25: 19659.51 | I25: 23187.346 | J25: 26913.303 | K25: 30810.607 | L25: 34887.918 | M25: 39154.323 | N25: 43619.366 | O25: 48293.067 | P25: 53185.947 | Q25: 58257.136 | R25: 63513.869 | S25: 68963.673 | T25: 74614.374 | U25: 80474.109 | V25: 86551.344 | W25: 92789.187 | X25: 99192.587 | Y25: 105766.64
A26: Gross Margin % | B26: 0.61200477 | C26: 0.74234958 | D26: 0.80727675 | E26: 0.84548741 | F26: 0.87060759 | G26: 0.88834331 | H26: 0.90123659 | I26: 0.91106292 | J26: 0.91879159 | K26: 0.92496835 | L26: 0.9300142 | M26: 0.93421045 | N26: 0.93775221 | O26: 0.94077906 | P26: 0.94339353 | Q26: 0.94565144 | R26: 0.94762016 | S26: 0.94935106 | T26: 0.95088403 | U26: 0.95225049 | V26: 0.95347555 | W26: 0.95456875 | X26: 0.95555008 | Y26: 0.95643567
A28: PERSONNEL
A29: CEO - David Youssef (G&A) | B29: 10000 | C29: 10000 | D29: 10000 | E29: 10000 | F29: 10000 | G29: 10000 | H29: 10000 | I29: 10000 | J29: 10000 | K29: 10000 | L29: 10000 | M29: 10000 | N29: 10000 | O29: 10000 | P29: 10000 | Q29: 10000 | R29: 10000 | S29: 10000 | T29: 10000 | U29: 10000 | V29: 10000 | W29: 10000 | X29: 10000 | Y29: 10000
A30: CTO - Igor Malovitsa (R&D) | B30: 10000 | C30: 10000 | D30: 10000 | E30: 10000 | F30: 10000 | G30: 10000 | H30: 10000 | I30: 10000 | J30: 10000 | K30: 10000 | L30: 10000 | M30: 10000 | N30: 10000 | O30: 10000 | P30: 10000 | Q30: 10000 | R30: 10000 | S30: 10000 | T30: 10000 | U30: 10000 | V30: 10000 | W30: 10000 | X30: 10000 | Y30: 10000
A31: GTM - Kristen Hengst Smith (S&M) | B31: 7000 | C31: 7000 | D31: 7000 | E31: 7000 | F31: 7000 | G31: 7000 | H31: 7000 | I31: 7000 | J31: 7000 | K31: 7000 | L31: 7000 | M31: 7000 | N31: 7000 | O31: 7000 | P31: 7000 | Q31: 7000 | R31: 7000 | S31: 7000 | T31: 7000 | U31: 7000 | V31: 7000 | W31: 7000 | X31: 7000 | Y31: 7000
A32: Engineer - Hire #1 (R&D) | B32: 0 | C32: 0 | D32: 0 | E32: 0 | F32: 0 | G32: 10000 | H32: 10000 | I32: 10000 | J32: 10000 | K32: 10000 | L32: 10000 | M32: 10000 | N32: 10000 | O32: 10000 | P32: 10000 | Q32: 10000 | R32: 10000 | S32: 10000 | T32: 10000 | U32: 10000 | V32: 10000 | W32: 10000 | X32: 10000 | Y32: 10000
A33: Total Payroll | B33: 27000 | C33: 27000 | D33: 27000 | E33: 27000 | F33: 27000 | G33: 37000 | H33: 37000 | I33: 37000 | J33: 37000 | K33: 37000 | L33: 37000 | M33: 37000 | N33: 37000 | O33: 37000 | P33: 37000 | Q33: 37000 | R33: 37000 | S33: 37000 | T33: 37000 | U33: 37000 | V33: 37000 | W33: 37000 | X33: 37000 | Y33: 37000 | Z33: 394000 | AA33: 444000
A35: OPERATING EXPENSES
A36: Sales & Marketing | B36: 7251.4 | C36: 7395.343 | D36: 7553.0863 | E36: 7722.8185 | F36: 7905.5018 | G36: 8102.1755 | H36: 8308.8357 | I36: 8527.0523 | J36: 8757.5239 | K36: 8998.5943 | L36: 9250.799 | M36: 9514.7004 | N36: 9790.8886 | O36: 10079.984 | P36: 10382.636 | Q36: 10696.318 | R36: 11021.476 | S36: 11358.578 | T36: 11708.106 | U36: 12070.563 | V36: 12446.475 | W36: 12832.321 | X36: 13228.407 | Y36: 13635.05 | Z36: 99287.831 | AA36: 139250.8
A37: S&M % of Revenue | B37: 1.7306444 | C37: 1.1223686 | D37: 0.81937519 | E37: 0.64105877 | F37: 0.52383123 | G37: 0.44106455 | H37: 0.3808959 | I37: 0.33503969 | J37: 0.29897257 | K37: 0.27014771 | L37: 0.2466004 | M37: 0.22701791 | N37: 0.2104897 | O37: 0.19636437 | P37: 0.18416353 | Q37: 0.1736266 | R37: 0.16443925 | S37: 0.15636171 | T37: 0.14920785 | U37: 0.14283103 | V37: 0.1371141 | W37: 0.1320125 | X37: 0.12743297 | Y37: 0.1233002
A38: Research & Development | B38: 13000 | C38: 13000 | D38: 13000 | E38: 13000 | F38: 13000 | G38: 23000 | H38: 23000 | I38: 23000 | J38: 23000 | K38: 23000 | L38: 23000 | M38: 23000 | N38: 23000 | O38: 23000 | P38: 23000 | Q38: 23000 | R38: 23000 | S38: 23000 | T38: 23000 | U38: 23000 | V38: 23000 | W38: 23000 | X38: 23000 | Y38: 23000 | Z38: 226000 | AA38: 276000
A39: R&D % of Revenue | B39: 3.1026253 | C39: 1.9729703 | D39: 1.4102682 | E39: 1.0791091 | F39: 0.86140086 | G39: 1.2520692 | H39: 1.0543722 | I39: 0.90370184 | J39: 0.78519559 | K39: 0.69048532 | L39: 0.6131156 | M39: 0.54877313 | N39: 0.49446617 | O39: 0.44805434 | P39: 0.40796587 | Q39: 0.37334454 | R39: 0.34315755 | S39: 0.31661705 | T39: 0.29311152 | U39: 0.2721591 | V39: 0.2533749 | W39: 0.2366125 | X39: 0.22156547 | Y39: 0.20798638
A40: General & Administrative | B40: 14867 | C40: 14867 | D40: 14867 | E40: 14867 | F40: 14867 | G40: 14867 | H40: 14867 | I40: 14867 | J40: 14867 | K40: 14867 | L40: 14867 | M40: 14867 | N40: 14867 | O40: 14867 | P40: 14867 | Q40: 14867 | R40: 14867 | S40: 14867 | T40: 14867 | U40: 14867 | V40: 14867 | W40: 14867 | X40: 14867 | Y40: 14867 | Z40: 178404 | AA40: 178404
A41: G&A % of Revenue | B41: 3.54821 | C41: 2.2563192 | D41: 1.6128044 | E41: 1.2340858 | F41: 0.98511127 | G41: 0.80932667 | H41: 0.68153704 | I41: 0.58414501 | J41: 0.5075436 | K41: 0.44632371 | L41: 0.39631259 | M41: 0.35472218 | N41: 0.31961863 | O41: 0.28961843 | P41: 0.26370559 | Q41: 0.24132666 | R41: 0.22181406 | S41: 0.20465851 | T41: 0.18946474 | U41: 0.17592128 | V41: 0.16377933 | W41: 0.15294426 | X41: 0.14321799 | Y41: 0.13444058
A42: Total OpEx | B42: 35118.4 | C42: 35262.343 | D42: 35420.086 | E42: 35589.818 | F42: 35772.502 | G42: 45969.175 | H42: 46175.836 | I42: 46394.052 | J42: 46624.524 | K42: 46865.594 | L42: 47117.799 | M42: 47381.7 | N42: 47657.889 | O42: 47946.984 | P42: 48249.636 | Q42: 48563.318 | R42: 48888.476 | S42: 49225.578 | T42: 49575.106 | U42: 49937.563 | V42: 50313.475 | W42: 50699.321 | X42: 51095.407 | Y42: 51502.05 | Z42: 503691.83 | AA42: 593654.8
A44: EBITDA / OPERATING INCOME
A45: EBITDA | B45: -32554.1 | C45: -30370.964 | D45: -27978.525 | E45: -25404.253 | F45: -22633.556 | G45: -29650.672 | H45: -26516.326 | I45: -23206.706 | J45: -19711.221 | K45: -16054.987 | L45: -12229.881 | M45: -8227.3778 | N45: -4038.5229 | O45: 346.0836 | P45: 4936.3113 | Q45: 9693.8179 | R45: 14625.392 | S45: 19738.095 | T45: 25039.268 | U45: 30536.546 | V45: 36237.869 | W45: 42089.866 | X45: 48097.18 | Y45: 54264.592 | Z45: -274538.57 | AA45: 281566.5
A46: EBITDA Margin % | B46: -7.7694749 | C46: -4.6093085 | D46: -3.0351711 | E46: -2.1087663 | F46: -1.4997358 | G46: -1.6141172 | H46: -1.2155686 | I46: -0.91182361 | J46: -0.67292018 | K46: -0.48198838 | L46: -0.3260144 | M46: -0.19630278 | N46: -0.086822302 | O46: 0.0067419244 | P46: 0.087558545 | Q46: 0.15735365 | R46: 0.2182093 | S46: 0.2717138 | T46: 0.31909991 | U46: 0.36133908 | V46: 0.39920723 | W46: 0.43299949 | X46: 0.46333366 | Y46: 0.49070851
A48: SaaS OPERATING METRICS
A49: CAC (S&M / New Customers) | B49: 7251.4 | C49: 7395.343 | D49: 3776.5431 | E49: 7722.8185 | F49: 3952.7509 | G49: 8102.1755 | H49: 4154.4178 | I49: 4263.5262 | J49: 4378.7619 | K49: 4499.2971 | L49: 4625.3995 | M49: 4757.3502 | N49: 0 | O49: 5039.9918 | P49: 3460.8786 | Q49: 5348.1588 | R49: 5510.7382 | S49: 3786.1926 | T49: 3902.7019 | U49: 6035.2817 | V49: 4148.825 | W49: 4277.4403 | X49: 4409.4692 | Y49: 4545.0167
A50: CAC Payback (months) | B50: 5.9243002 | C50: 4.981038 | D50: 2.3390635 | E50: 4.5670807 | F50: 2.2701105 | G50: 4.5602727 | H50: 2.3048431 | I50: 2.3398637 | J50: 2.3828918 | K50: 2.4321357 | L50: 2.486736 | M50: 2.5461876 | N50: 0 | O50: 2.4351151 | P50: 1.667519 | Q50: 2.5706948 | R50: 2.6433387 | S50: 1.8128137 | T50: 1.8655854 | U50: 2.88087 | V50: 1.9778478 | W50: 2.0368266 | X50: 2.0975396 | Y50: 2.1600163
A51: LTV (margin-weighted) | B51: 244801.91 | C51: 296939.83 | D51: 322910.7 | E51: 338194.96 | F51: 348243.04 | G51: 355337.32 | H51: 300412.2 | I51: 303687.64 | J51: 306263.86 | K51: 308322.78 | L51: 310004.73 | M51: 311403.48 | N51: 343842.48 | O51: 344952.32 | P51: 345910.96 | Q51: 346738.86 | R51: 347460.73 | S51: 348095.39 | T51: 348657.48 | U51: 349158.51 | V51: 349607.7 | W51: 350008.54 | X51: 350368.36 | Y51: 350693.08
A52: LTV:CAC Ratio | B52: 33.759262 | C52: 40.152273 | D52: 85.504305 | E52: 43.79165 | F52: 88.101438 | G52: 43.857027 | H52: 72.311503 | I52: 71.229219 | J52: 69.943027 | K52: 68.526877 | L52: 67.022261 | M52: 65.457339 | N52: 0 | O52: 68.443033 | P52: 99.948885 | Q52: 64.833314 | R52: 63.051575 | S52: 91.93811 | T52: 89.337462 | U52: 57.852894 | V52: 84.266679 | W52: 81.826634 | X52: 79.458173 | Y52: 77.15991
A53: Net Revenue Retention | B53: 1 | C53: 1.5725656 | D53: 1.3990036 | E53: 1.3068819 | F53: 1.2527375 | G53: 1.2171986 | H53: 1.1875021 | I53: 1.1667258 | J53: 1.1509258 | K53: 1.1371648 | L53: 1.1261911 | M53: 1.1172478 | N53: 1.1098295 | O53: 1.1035853 | P53: 1.0982643 | Q53: 1.0927329 | R53: 1.0879683 | S53: 1.0838253 | T53: 1.0801931 | U53: 1.0769859 | V53: 1.074136 | W53: 1.0708432 | X53: 1.0679124 | Y53: 1.0652884
A54: Gross Revenue Retention | B54: 0.995 | C54: 0.995 | D54: 0.995 | E54: 0.995 | F54: 0.995 | G54: 0.995 | H54: 0.994 | I54: 0.994 | J54: 0.994 | K54: 0.994 | L54: 0.994 | M54: 0.994 | N54: 0.994 | O54: 0.994 | P54: 0.994 | Q54: 0.994 | R54: 0.994 | S54: 0.994 | T54: 0.994 | U54: 0.994 | V54: 0.994 | W54: 0.994 | X54: 0.994 | Y54: 0.994
A55: Rule of 40 | B55: -7.7694749 | C55: 2.261479 | D55: 1.7528723 | E55: 1.5738165 | F55: 1.533114 | G55: 0.99226571 | H55: 1.0344567 | I55: 1.0888858 | J55: 1.1381889 | K55: 1.1639891 | L55: 1.1882785 | M55: 1.2106714 | N55: 1.2311315 | O55: 1.2497651 | P55: 1.2667299 | Q55: 1.2701489 | R55: 1.2738288 | S55: 1.2776168 | T55: 1.2814172 | U55: 1.2851702 | V55: 1.2888395 | W55: 1.2831185 | X55: 1.2782819 | Y55: 1.2741689
A57: CASH & RUNWAY ($1M Raise)
A58: Monthly Burn (neg=profit) | B58: 32554.1 | C58: 30370.964 | D58: 27978.525 | E58: 25404.253 | F58: 22633.556 | G58: 29650.672 | H58: 26516.326 | I58: 23206.706 | J58: 19711.221 | K58: 16054.987 | L58: 12229.881 | M58: 8227.3778 | N58: 4038.5229 | O58: -346.0836 | P58: -4936.3113 | Q58: -9693.8179 | R58: -14625.392 | S58: -19738.095 | T58: -25039.268 | U58: -30536.546 | V58: -36237.869 | W58: -42089.866 | X58: -48097.18 | Y58: -54264.592
A59: Cumulative Cash | B59: 967445.9 | C59: 937074.94 | D59: 909096.41 | E59: 883692.16 | F59: 861058.6 | G59: 831407.93 | H59: 804891.6 | I59: 781684.9 | J59: 761973.68 | K59: 745918.69 | L59: 733688.81 | M59: 725461.43 | N59: 721422.91 | O59: 721768.99 | P59: 726705.3 | Q59: 736399.12 | R59: 751024.51 | S59: 770762.61 | T59: 795801.87 | U59: 826338.42 | V59: 862576.29 | W59: 904666.16 | X59: 952763.34 | Y59: 1007027.9
A60: Runway (months) | B60: 29.718097 | C60: 30.854303 | D60: 32.49265 | E60: 34.785205 | F60: 38.043451 | G60: 28.040104 | H60: 30.354568 | I60: 33.683578 | J60: 38.656848 | K60: 46.460249 | L60: 59.99149 | M60: 88.176506 | N60: 178.63534 | O60: 99 | P60: 99 | Q60: 99 | R60: 99 | S60: 99 | T60: 99 | U60: 99 | V60: 99 | W60: 99 | X60: 99 | Y60: 99
A62: EBITDA Breakeven: Month 14 (Feb-2027)

Sheet Bull Case P&L
A1: GuardSpine SaaS P&L -- Bull Case (AI Adoption Wave)
A2: Generated: Feb 18, 2026 | $1M raise at $9M pre / $10M post
A4: Metric | B4: Year 1 | N4: Year 2 | Z4: Y1 Total | AA4: Y2 Total
A5: Month | B5: Jan-2026 | C5: Feb-2026 | D5: Mar-2026 | E5: Apr-2026 | F5: May-2026 | G5: Jun-2026 | H5: Jul-2026 | I5: Aug-2026 | J5: Sep-2026 | K5: Oct-2026 | L5: Nov-2026 | M5: Dec-2026 | N5: Jan-2027 | O5: Feb-2027 | P5: Mar-2027 | Q5: Apr-2027 | R5: May-2027 | S5: Jun-2027 | T5: Jul-2027 | U5: Aug-2027 | V5: Sep-2027 | W5: Oct-2027 | X5: Nov-2027 | Y5: Dec-2027
A6: Month # | B6: 1 | C6: 2 | D6: 3 | E6: 4 | F6: 5 | G6: 6 | H6: 7 | I6: 8 | J6: 9 | K6: 10 | L6: 11 | M6: 12 | N6: 13 | O6: 14 | P6: 15 | Q6: 16 | R6: 17 | S6: 18 | T6: 19 | U6: 20 | V6: 21 | W6: 22 | X6: 23 | Y6: 24
A8: REVENUE
A9: Avg Price / Customer | B9: 3500 | C9: 3500 | D9: 3500 | E9: 3500 | F9: 3500 | G9: 3500 | H9: 3500 | I9: 3500 | J9: 3500 | K9: 3500 | L9: 3500 | M9: 3500 | N9: 4200 | O9: 4200 | P9: 4200 | Q9: 4200 | R9: 4200 | S9: 4200 | T9: 4200 | U9: 4200 | V9: 4200 | W9: 4200 | X9: 4200 | Y9: 4200
A10: Customers | B10: 4 | C10: 7 | D10: 10 | E10: 14 | F10: 18 | G10: 23 | H10: 29 | I10: 35 | J10: 42 | K10: 50 | L10: 59 | M10: 69 | N10: 66 | O10: 76 | P10: 87 | Q10: 98 | R10: 111 | S10: 125 | T10: 140 | U10: 156 | V10: 173 | W10: 192 | X10: 212 | Y10: 233
A11: New Customers | B11: 2 | C11: 3 | D11: 3 | E11: 4 | F11: 4 | G11: 5 | H11: 6 | I11: 6 | J11: 7 | K11: 8 | L11: 9 | M11: 10 | N11: 0 | O11: 10 | P11: 11 | Q11: 11 | R11: 13 | S11: 14 | T11: 15 | U11: 16 | V11: 17 | W11: 19 | X11: 20 | Y11: 21
A12: Gross MRR | B12: 15246 | C12: 24962.308 | D12: 36413.607 | E12: 49567.188 | F12: 64678.422 | G12: 82040.989 | H12: 101560.74 | I12: 123591.5 | J12: 148459.77 | K12: 176029.73 | L12: 206598.66 | M12: 240496.57 | N12: 277744.55 | O12: 318677.73 | P12: 363664.76 | Q12: 412651.7 | R12: 465998.69 | S12: 524098.29 | T12: 586783.39 | U12: 654421.04 | V12: 727407.61 | W12: 805421.7 | X12: 888815.5 | Y12: 977965.82 | Z12: 1269645.5 | AA12: 7003650.8
A13: Lost MRR (Churn) | B13: 14 | C13: 30.492 | D13: 49.924616 | E13: 72.827215 | F13: 99.134376 | G13: 129.35684 | H13: 246.12297 | I13: 304.68222 | J13: 370.77449 | K13: 445.3793 | L13: 528.08918 | M13: 619.79599 | N13: 721.48971 | O13: 833.23365 | P13: 956.0332 | Q13: 1090.9943 | R13: 1237.9551 | S13: 1397.9961 | T13: 1572.2949 | U13: 1760.3502 | V13: 1963.2631 | W13: 2182.2228 | X13: 2416.2651 | Y13: 2666.4465
A14: Net MRR | B14: 15232 | C14: 24931.816 | D14: 36363.683 | E14: 49494.361 | F14: 64579.288 | G14: 81911.632 | H14: 101314.62 | I14: 123286.81 | J14: 148088.99 | K14: 175584.35 | L14: 206070.58 | M14: 239876.77 | N14: 277023.06 | O14: 317844.5 | P14: 362708.72 | Q14: 411560.7 | R14: 464760.74 | S14: 522700.29 | T14: 585211.1 | U14: 652660.69 | V14: 725444.34 | W14: 803239.48 | X14: 886399.24 | Y14: 975299.38
A15: ARR (MRR x 12) | B15: 182952 | C15: 299547.7 | D15: 436963.29 | E15: 594806.25 | F15: 776141.07 | G15: 984491.87 | H15: 1218728.9 | I15: 1483098 | J15: 1781517.2 | K15: 2112356.7 | L15: 2479184 | M15: 2885958.8 | N15: 3332934.6 | O15: 3824132.8 | P15: 4363977.1 | Q15: 4951820.4 | R15: 5591984.3 | S15: 6289179.5 | T15: 7041400.7 | U15: 7853052.4 | V15: 8728891.3 | W15: 9665060.4 | X15: 10665786 | Y15: 11735590
A16: MRR Growth Rate | B16: 0 | C16: 0.63730211 | D16: 0.45874361 | E16: 0.36122706 | F16: 0.30486366 | G16: 0.26844451 | H16: 0.23792681 | I16: 0.21692197 | J16: 0.20121344 | K16: 0.18570661 | L16: 0.17365782 | M16: 0.1640761 | N16: 0.15487947 | O16: 0.14737709 | P16: 0.14116777 | Q16: 0.13470357 | R16: 0.1292785 | S16: 0.1246776 | T16: 0.11960563 | U16: 0.1152685 | V16: 0.11152846 | W16: 0.10724949 | X16: 0.10354054 | Y16: 0.10030239
A18: COST OF GOODS SOLD
A19: Payment Processing (3%) | B19: 457.38 | C19: 748.86924 | D19: 1092.4082 | E19: 1487.0156 | F19: 1940.3527 | G19: 2461.2297 | H19: 3046.8222 | I19: 3707.7449 | J19: 4453.793 | K19: 5280.8918 | L19: 6197.9599 | M19: 7214.8971 | N19: 8332.3365 | O19: 9560.332 | P19: 10909.943 | Q19: 12379.551 | R19: 13979.961 | S19: 15722.949 | T19: 17603.502 | U19: 19632.631 | V19: 21822.228 | W19: 24162.651 | X19: 26664.465 | Y19: 29338.975
A20: Hosting & Bandwidth | B20: 1500 | C20: 1500 | D20: 1500 | E20: 1500 | F20: 1500 | G20: 1500 | H20: 1500 | I20: 1500 | J20: 1500 | K20: 1500 | L20: 1500 | M20: 1500 | N20: 1500 | O20: 1500 | P20: 1500 | Q20: 1500 | R20: 1500 | S20: 1500 | T20: 1500 | U20: 1500 | V20: 1500 | W20: 1500 | X20: 1500 | Y20: 1500
A21: Total COGS | B21: 1957.38 | C21: 2248.8692 | D21: 2592.4082 | E21: 2987.0156 | F21: 3440.3527 | G21: 3961.2297 | H21: 4546.8222 | I21: 5207.7449 | J21: 5953.793 | K21: 6780.8918 | L21: 7697.9599 | M21: 8714.8971 | N21: 9832.3365 | O21: 11060.332 | P21: 12409.943 | Q21: 13879.551 | R21: 15479.961 | S21: 17222.949 | T21: 19103.502 | U21: 21132.631 | V21: 23322.228 | W21: 25662.651 | X21: 28164.465 | Y21: 30838.975 | Z21: 56089.364 | AA21: 228109.52
A22: COGS % of Revenue | B22: 0.12838646 | C22: 0.090090597 | D22: 0.071193392 | E22: 0.060261955 | F22: 0.05319166 | G22: 0.048283544 | H22: 0.044769487 | I22: 0.042136757 | J22: 0.040103748 | K22: 0.038521288 | L22: 0.037260454 | M22: 0.036237095 | N22: 0.035400646 | O22: 0.03470695 | P22: 0.034124678 | Q22: 0.033635027 | R22: 0.033218893 | S22: 0.032862059 | T22: 0.03255631 | U22: 0.032292102 | V22: 0.032062118 | W22: 0.031862378 | X22: 0.031687639 | Y22: 0.031533796
A24: GROSS PROFIT
A25: Gross Profit | B25: 13288.62 | C25: 22713.439 | D25: 33821.199 | E25: 46580.172 | F25: 61238.069 | G25: 78079.76 | H25: 97013.918 | I25: 118383.75 | J25: 142505.97 | K25: 169248.83 | L25: 198900.7 | M25: 231781.67 | N25: 267912.21 | O25: 307617.4 | P25: 351254.81 | Q25: 398772.15 | R25: 450518.73 | S25: 506875.34 | T25: 567679.89 | U25: 633288.41 | V25: 704085.38 | W25: 779759.05 | X25: 860651.04 | Y25: 947126.85
A26: Gross Margin % | B26: 0.87161354 | C26: 0.9099094 | D26: 0.92880661 | E26: 0.93973805 | F26: 0.94680834 | G26: 0.95171646 | H26: 0.95523051 | I26: 0.95786324 | J26: 0.95989625 | K26: 0.96147871 | L26: 0.96273955 | M26: 0.9637629 | N26: 0.96459935 | O26: 0.96529305 | P26: 0.96587532 | Q26: 0.96636497 | R26: 0.96678111 | S26: 0.96713794 | T26: 0.96744369 | U26: 0.9677079 | V26: 0.96793788 | W26: 0.96813762 | X26: 0.96831236 | Y26: 0.9684662
A28: PERSONNEL
A29: CEO - David Youssef (G&A) | B29: 10000 | C29: 10000 | D29: 10000 | E29: 10000 | F29: 10000 | G29: 10000 | H29: 10000 | I29: 10000 | J29: 10000 | K29: 10000 | L29: 10000 | M29: 10000 | N29: 10000 | O29: 10000 | P29: 10000 | Q29: 10000 | R29: 10000 | S29: 10000 | T29: 10000 | U29: 10000 | V29: 10000 | W29: 10000 | X29: 10000 | Y29: 10000
A30: CTO - Igor Malovitsa (R&D) | B30: 10000 | C30: 10000 | D30: 10000 | E30: 10000 | F30: 10000 | G30: 10000 | H30: 10000 | I30: 10000 | J30: 10000 | K30: 10000 | L30: 10000 | M30: 10000 | N30: 10000 | O30: 10000 | P30: 10000 | Q30: 10000 | R30: 10000 | S30: 10000 | T30: 10000 | U30: 10000 | V30: 10000 | W30: 10000 | X30: 10000 | Y30: 10000
A31: GTM - Kristen Hengst Smith (S&M) | B31: 7000 | C31: 7000 | D31: 7000 | E31: 7000 | F31: 7000 | G31: 7000 | H31: 7000 | I31: 7000 | J31: 7000 | K31: 7000 | L31: 7000 | M31: 7000 | N31: 7000 | O31: 7000 | P31: 7000 | Q31: 7000 | R31: 7000 | S31: 7000 | T31: 7000 | U31: 7000 | V31: 7000 | W31: 7000 | X31: 7000 | Y31: 7000
A32: Engineer - Hire #1 (R&D) | B32: 0 | C32: 0 | D32: 10000 | E32: 10000 | F32: 10000 | G32: 10000 | H32: 10000 | I32: 10000 | J32: 10000 | K32: 10000 | L32: 10000 | M32: 10000 | N32: 10000 | O32: 10000 | P32: 10000 | Q32: 10000 | R32: 10000 | S32: 10000 | T32: 10000 | U32: 10000 | V32: 10000 | W32: 10000 | X32: 10000 | Y32: 10000
A33: Engineer - Hire #2 (R&D) | B33: 0 | C33: 0 | D33: 0 | E33: 0 | F33: 0 | G33: 0 | H33: 10000 | I33: 10000 | J33: 10000 | K33: 10000 | L33: 10000 | M33: 10000 | N33: 10000 | O33: 10000 | P33: 10000 | Q33: 10000 | R33: 10000 | S33: 10000 | T33: 10000 | U33: 10000 | V33: 10000 | W33: 10000 | X33: 10000 | Y33: 10000
A34: Sales - SDR Hire (S&M) | B34: 0 | C34: 0 | D34: 0 | E34: 0 | F34: 0 | G34: 0 | H34: 0 | I34: 0 | J34: 6000 | K34: 6000 | L34: 6000 | M34: 6000 | N34: 6000 | O34: 6000 | P34: 6000 | Q34: 6000 | R34: 6000 | S34: 6000 | T34: 6000 | U34: 6000 | V34: 6000 | W34: 6000 | X34: 6000 | Y34: 6000
A35: Total Payroll | B35: 27000 | C35: 27000 | D35: 37000 | E35: 37000 | F35: 37000 | G35: 37000 | H35: 47000 | I35: 47000 | J35: 53000 | K35: 53000 | L35: 53000 | M35: 53000 | N35: 53000 | O35: 53000 | P35: 53000 | Q35: 53000 | R35: 53000 | S35: 53000 | T35: 53000 | U35: 53000 | V35: 53000 | W35: 53000 | X35: 53000 | Y35: 53000 | Z35: 508000 | AA35: 636000
A37: OPERATING EXPENSES
A38: Sales & Marketing | B38: 7914.76 | C38: 8497.7385 | D38: 9184.8164 | E38: 9974.0313 | F38: 10880.705 | G38: 11922.459 | H38: 13093.644 | I38: 14415.49 | J38: 21907.586 | K38: 23561.784 | L38: 25395.92 | M38: 27429.794 | N38: 29664.673 | O38: 32120.664 | P38: 34819.885 | Q38: 37759.102 | R38: 40959.921 | S38: 44445.897 | T38: 48207.004 | U38: 52265.262 | V38: 56644.456 | W38: 61325.302 | X38: 66328.93 | Y38: 71677.949 | Z38: 184178.73 | AA38: 576219.05
A39: S&M % of Revenue | B39: 0.51913682 | C39: 0.34042279 | D39: 0.25223583 | E39: 0.20122246 | F39: 0.16822775 | G39: 0.1453232 | H39: 0.12892427 | I39: 0.1166382 | J39: 0.14756581 | K39: 0.13385116 | L39: 0.12292393 | M39: 0.11405483 | N39: 0.1068056 | O39: 0.10079356 | P39: 0.095747209 | Q39: 0.091503566 | R39: 0.087897074 | S39: 0.084804508 | T39: 0.082154683 | U39: 0.079864887 | V39: 0.077871686 | W39: 0.076140613 | X39: 0.074626208 | Y39: 0.073292898
A40: Research & Development | B40: 13000 | C40: 13000 | D40: 23000 | E40: 23000 | F40: 23000 | G40: 23000 | H40: 33000 | I40: 33000 | J40: 33000 | K40: 33000 | L40: 33000 | M40: 33000 | N40: 33000 | O40: 33000 | P40: 33000 | Q40: 33000 | R40: 33000 | S40: 33000 | T40: 33000 | U40: 33000 | V40: 33000 | W40: 33000 | X40: 33000 | Y40: 33000 | Z40: 316000 | AA40: 396000
A41: R&D % of Revenue | B41: 0.85268267 | C41: 0.52078518 | D41: 0.63163201 | E41: 0.46401664 | F41: 0.35560546 | G41: 0.28034767 | H41: 0.32492871 | I41: 0.26700866 | J41: 0.22228245 | K41: 0.18746834 | L41: 0.15972998 | M41: 0.13721609 | N41: 0.11881421 | O41: 0.10355289 | P41: 0.090742914 | Q41: 0.079970591 | R41: 0.07081565 | S41: 0.062965289 | T41: 0.05623881 | U41: 0.050426252 | V41: 0.045366586 | W41: 0.040972325 | X41: 0.037128065 | Y41: 0.033743511
A42: General & Administrative | B42: 14867 | C42: 14867 | D42: 14867 | E42: 14867 | F42: 14867 | G42: 14867 | H42: 14867 | I42: 14867 | J42: 14867 | K42: 14867 | L42: 14867 | M42: 14867 | N42: 14867 | O42: 14867 | P42: 14867 | Q42: 14867 | R42: 14867 | S42: 14867 | T42: 14867 | U42: 14867 | V42: 14867 | W42: 14867 | X42: 14867 | Y42: 14867 | Z42: 178404 | AA42: 178404
A43: G&A % of Revenue | B43: 0.97514102 | C43: 0.59557794 | D43: 0.40828144 | E43: 0.29993632 | F43: 0.22986028 | G43: 0.18121429 | H43: 0.14638531 | I43: 0.12029145 | J43: 0.10014161 | K43: 0.084457326 | L43: 0.071960775 | M43: 0.06181793 | N43: 0.053527603 | O43: 0.046652146 | P43: 0.040881058 | Q43: 0.036027963 | R43: 0.031903523 | S43: 0.028366817 | T43: 0.025336436 | U43: 0.02271779 | V43: 0.020438335 | W43: 0.018458653 | X43: 0.016726756 | Y43: 0.015201963
A44: Total OpEx | B44: 35781.76 | C44: 36364.738 | D44: 47051.816 | E44: 47841.031 | F44: 48747.705 | G44: 49789.459 | H44: 60960.644 | I44: 62282.49 | J44: 69774.586 | K44: 71428.784 | L44: 73262.92 | M44: 75296.794 | N44: 77531.673 | O44: 79987.664 | P44: 82686.885 | Q44: 85626.102 | R44: 88826.921 | S44: 92312.897 | T44: 96074.004 | U44: 100132.26 | V44: 104511.46 | W44: 109192.3 | X44: 114195.93 | Y44: 119544.95 | Z44: 678582.73 | AA44: 1150623
A46: EBITDA / OPERATING INCOME
A47: EBITDA | B47: -22493.14 | C47: -13651.3 | D47: -13230.617 | E47: -1260.8591 | F47: 12490.364 | G47: 28290.3 | H47: 36053.274 | I47: 56101.261 | J47: 72731.387 | K47: 97820.051 | L47: 125637.78 | M47: 156484.88 | N47: 190380.54 | O47: 227629.74 | P47: 268567.93 | Q47: 313146.04 | R47: 361691.81 | S47: 414562.44 | T47: 471605.89 | U47: 533156.14 | V47: 599573.92 | W47: 670566.75 | X47: 746455.11 | Y47: 827581.9 | Z47: 534973.38 | AA47: 5624918.2
A48: EBITDA Margin % | B48: -1.475347 | C48: -0.5468765 | D48: -0.36334267 | E48: -0.025437375 | F48: 0.19311486 | G48: 0.34483129 | H48: 0.35499223 | I48: 0.45392493 | J48: 0.48990638 | K48: 0.55570189 | L48: 0.60812486 | M48: 0.65067405 | N48: 0.68545194 | O48: 0.71429445 | P48: 0.73850414 | Q48: 0.75886285 | R48: 0.77616486 | S48: 0.79100133 | T48: 0.80371376 | U48: 0.81469897 | V48: 0.82426128 | W48: 0.83256603 | X48: 0.83983133 | Y48: 0.84622783
A50: SaaS OPERATING METRICS
A51: CAC (S&M / New Customers) | B51: 3957.38 | C51: 2832.5795 | D51: 3061.6055 | E51: 2493.5078 | F51: 2720.1763 | G51: 2384.4919 | H51: 2182.2741 | I51: 2402.5816 | J51: 3129.6551 | K51: 2945.223 | L51: 2821.7689 | M51: 2742.9794 | N51: 0 | O51: 3212.0664 | P51: 3165.4441 | Q51: 3432.6456 | R51: 3150.7632 | S51: 3174.7069 | T51: 3213.8002 | U51: 3266.5789 | V51: 3332.0268 | W51: 3227.6475 | X51: 3316.4465 | Y51: 3413.2357
A52: CAC Payback (months) | B52: 1.2972263 | C52: 0.88943847 | D52: 0.94179393 | E52: 0.75811638 | F52: 0.82085593 | G52: 0.71584702 | H52: 0.65272923 | I52: 0.71664917 | J52: 0.93154565 | K52: 0.87520635 | L52: 0.83742242 | M52: 0.81317552 | N52: 0 | O52: 0.79227517 | P52: 0.78030483 | Q52: 0.84574317 | R52: 0.77595818 | S52: 0.78156649 | T52: 0.79094064 | U52: 0.80371038 | V52: 0.81961843 | W52: 0.79377919 | X52: 0.81547045 | Y52: 0.83913632
A53: LTV (margin-weighted) | B53: 1525323.7 | C53: 1592341.5 | D53: 1625411.6 | E53: 1644541.6 | F53: 1656914.6 | G53: 1665503.8 | H53: 1114435.6 | I53: 1117507.1 | J53: 1119879 | K53: 1121725.2 | L53: 1123196.1 | M53: 1124390.1 | N53: 1350439.1 | O53: 1351410.3 | P53: 1352225.5 | Q53: 1352911 | R53: 1353493.5 | S53: 1353993.1 | T53: 1354421.2 | U53: 1354791.1 | V53: 1355113 | W53: 1355392.7 | X53: 1355637.3 | Y53: 1355852.7
A54: LTV:CAC Ratio | B54: 385.43776 | C54: 562.15243 | D54: 530.9017 | E54: 659.52935 | F54: 609.12029 | G54: 698.47325 | H54: 510.67628 | I54: 465.12764 | J54: 357.82823 | K54: 380.86256 | L54: 398.04682 | M54: 409.9156 | N54: 0 | O54: 420.72925 | P54: 427.18348 | Q54: 394.13068 | R54: 429.57641 | S54: 426.49389 | T54: 421.43913 | U54: 414.7431 | V54: 406.69331 | W54: 419.93206 | X54: 408.762 | Y54: 397.23383
A55: Net Revenue Retention | B55: 1 | C55: 1.6373021 | D55: 1.4587436 | E55: 1.3612271 | F55: 1.3048637 | G55: 1.2684445 | H55: 1.2379268 | I55: 1.216922 | J55: 1.2012134 | K55: 1.1857066 | L55: 1.1736578 | M55: 1.1640761 | N55: 1.1548795 | O55: 1.1473771 | P55: 1.1411678 | Q55: 1.1347036 | R55: 1.1292785 | S55: 1.1246776 | T55: 1.1196056 | U55: 1.1152685 | V55: 1.1115285 | W55: 1.1072495 | X55: 1.1035405 | Y55: 1.1003024
A56: Gross Revenue Retention | B56: 0.998 | C56: 0.998 | D56: 0.998 | E56: 0.998 | F56: 0.998 | G56: 0.998 | H56: 0.997 | I56: 0.997 | J56: 0.997 | K56: 0.997 | L56: 0.997 | M56: 0.997 | N56: 0.997 | O56: 0.997 | P56: 0.997 | Q56: 0.997 | R56: 0.997 | S56: 0.997 | T56: 0.997 | U56: 0.997 | V56: 0.997 | W56: 0.997 | X56: 0.997 | Y56: 0.997
A57: Rule of 40 | B57: -1.475347 | C57: 7.1007488 | D57: 5.1415807 | E57: 4.3092874 | F57: 3.8514788 | G57: 3.5661654 | H57: 3.210114 | I57: 3.0569885 | J57: 2.9044677 | K57: 2.7841812 | L57: 2.6920187 | M57: 2.6195873 | N57: 2.5440055 | O57: 2.4828195 | P57: 2.4325174 | Q57: 2.3753056 | R57: 2.3275069 | S57: 2.2871325 | T57: 2.2389813 | U57: 2.197921 | V57: 2.1626028 | W57: 2.11956 | X57: 2.0823178 | Y57: 2.0498565
A59: CASH & RUNWAY ($1M Raise)
A60: Monthly Burn (neg=profit) | B60: 22493.14 | C60: 13651.3 | D60: 13230.617 | E60: 1260.8591 | F60: -12490.364 | G60: -28290.3 | H60: -36053.274 | I60: -56101.261 | J60: -72731.387 | K60: -97820.051 | L60: -125637.78 | M60: -156484.88 | N60: -190380.54 | O60: -227629.74 | P60: -268567.93 | Q60: -313146.04 | R60: -361691.81 | S60: -414562.44 | T60: -471605.89 | U60: -533156.14 | V60: -599573.92 | W60: -670566.75 | X60: -746455.11 | Y60: -827581.9
A61: Cumulative Cash | B61: 977506.86 | C61: 963855.56 | D61: 950624.94 | E61: 949364.08 | F61: 961854.45 | G61: 990144.75 | H61: 1026198 | I61: 1082299.3 | J61: 1155030.7 | K61: 1252850.7 | L61: 1378488.5 | M61: 1534973.4 | N61: 1725353.9 | O61: 1952983.7 | P61: 2221551.6 | Q61: 2534697.6 | R61: 2896389.4 | S61: 3310951.9 | T61: 3782557.8 | U61: 4315713.9 | V61: 4915287.8 | W61: 5585854.6 | X61: 6332309.7 | Y61: 7159891.6
A62: Runway (months) | B62: 43.457999 | C62: 70.605406 | D62: 71.850385 | E62: 752.95016 | F62: 99 | G62: 99 | H62: 99 | I62: 99 | J62: 99 | K62: 99 | L62: 99 | M62: 99 | N62: 99 | O62: 99 | P62: 99 | Q62: 99 | R62: 99 | S62: 99 | T62: 99 | U62: 99 | V62: 99 | W62: 99 | X62: 99 | Y62: 99
A64: EBITDA Breakeven: Month 5 (May-2026)
